{"uri":"http://labs.nypl.org/playbills-10-00637","template_id":"510feb5ac44ecc0002000001","assets":[{"id":"514a25a30f7ca625870000b9","width":1000,"height":1506,"uri":"https://s3.amazonaws.com/programs-cropped.nypl.org/10/00637.jpg","thumb_uri":"https://s3.amazonaws.com/programs-cropped.nypl.org/thumbs/10/00637.jpg"},{"id":"514a25a50f7ca625870000ba","width":1000,"height":1515,"uri":"https://s3.amazonaws.com/programs-cropped.nypl.org/10/00638.1.jpg","thumb_uri":"https://s3.amazonaws.com/programs-cropped.nypl.org/thumbs/10/00638.1.jpg"},{"id":"514a25a80f7ca625870000bb","width":1000,"height":1515,"uri":"https://s3.amazonaws.com/programs-cropped.nypl.org/10/00638.2.jpg","thumb_uri":"https://s3.amazonaws.com/programs-cropped.nypl.org/thumbs/10/00638.2.jpg"},{"id":"514a25ab0f7ca625870000bc","width":1000,"height":1509,"uri":"https://s3.amazonaws.com/programs-cropped.nypl.org/10/00639.1.jpg","thumb_uri":"https://s3.amazonaws.com/programs-cropped.nypl.org/thumbs/10/00639.1.jpg"},{"id":"514a25af0f7ca625870000bd","width":1000,"height":1509,"uri":"https://s3.amazonaws.com/programs-cropped.nypl.org/10/00639.2.jpg","thumb_uri":"https://s3.amazonaws.com/programs-cropped.nypl.org/thumbs/10/00639.2.jpg"},{"id":"514a25b10f7ca625870000be","width":1000,"height":1519,"uri":"https://s3.amazonaws.com/programs-cropped.nypl.org/10/00640.1.jpg","thumb_uri":"https://s3.amazonaws.com/programs-cropped.nypl.org/thumbs/10/00640.1.jpg"},{"id":"514a25b40f7ca625870000bf","width":1000,"height":1519,"uri":"https://s3.amazonaws.com/programs-cropped.nypl.org/10/00640.2.jpg","thumb_uri":"https://s3.amazonaws.com/programs-cropped.nypl.org/thumbs/10/00640.2.jpg"},{"id":"514a25b70f7ca625870000c0","width":1000,"height":1518,"uri":"https://s3.amazonaws.com/programs-cropped.nypl.org/10/00641.1.jpg","thumb_uri":"https://s3.amazonaws.com/programs-cropped.nypl.org/thumbs/10/00641.1.jpg"},{"id":"514a25ba0f7ca625870000c1","width":1000,"height":1518,"uri":"https://s3.amazonaws.com/programs-cropped.nypl.org/10/00641.2.jpg","thumb_uri":"https://s3.amazonaws.com/programs-cropped.nypl.org/thumbs/10/00641.2.jpg"},{"id":"514a25bd0f7ca625870000c2","width":1000,"height":1503,"uri":"https://s3.amazonaws.com/programs-cropped.nypl.org/10/00642.1.jpg","thumb_uri":"https://s3.amazonaws.com/programs-cropped.nypl.org/thumbs/10/00642.1.jpg"},{"id":"514a25c00f7ca625870000c3","width":1000,"height":1503,"uri":"https://s3.amazonaws.com/programs-cropped.nypl.org/10/00642.2.jpg","thumb_uri":"https://s3.amazonaws.com/programs-cropped.nypl.org/thumbs/10/00642.2.jpg"},{"id":"514a25c30f7ca625870000c4","width":1000,"height":1503,"uri":"https://s3.amazonaws.com/programs-cropped.nypl.org/10/00643.jpg","thumb_uri":"https://s3.amazonaws.com/programs-cropped.nypl.org/thumbs/10/00643.jpg"}],"transcription":{"annotations":[{"name":"Cast Member","entity_id":"510feb5ac44ecc000200000c","confidence":"medium","asset_id":"514a25a30f7ca625870000b9","bounds":{"width":"0.6694214876033058","height":"0.01555352241537054","x":"0.11983471074380166","y":"0.6395242451967064"},"data":{"character":{"value":"Jack North","confidence":"medium"},"description":{"value":"","confidence":"medium"},"actor":{"value":"Bobby Barry","confidence":"medium"}},"revisions":[{"id":"52527b2959df6000020058a1","user":{"name":"User.52525b1bd2b68b00020006c5","id":"52525b1bd2b68b00020006c5"},"asset_id":"514a25a30f7ca625870000b9","bounds":{"width":"0.6694214876033058","height":"0.01555352241537054","x":"0.11983471074380166","y":"0.6395242451967064"},"data":{"character":"Jack North","description":"","actor":"Bobby Barry"},"entity_id":"510feb5ac44ecc000200000c","created_at":"2013-10-07T09:13:13Z"},{"id":"525ffc10ad1f4c0002026912","user":{"name":"User.525ff191ad1f4c0002000225","id":"525ff191ad1f4c0002000225"},"asset_id":"514a25a30f7ca625870000b9","bounds":{"width":"0.7052631578947368","height":"0.02445414847161572","x":"0.09210526315789473","y":"0.6314410480349345"},"data":{"character":"Jack North","description":"","actor":"Bobby Barry"},"entity_id":"510feb5ac44ecc000200000c","created_at":"2013-10-17T15:02:40Z"}]},{"name":"Cast Member","entity_id":"510feb5ac44ecc000200000c","confidence":"medium","asset_id":"514a25a30f7ca625870000b9","bounds":{"width":"0.6680440771349863","height":"0.013723696248856358","x":"0.12258953168044077","y":"0.5580969807868252"},"data":{"character":{"value":"Helen West","confidence":"medium"},"description":{"value":"","confidence":"medium"},"actor":{"value":"Grace Tyson","confidence":"medium"}},"revisions":[{"id":"52527b2959df600002005895","user":{"name":"User.52525b1bd2b68b00020006c5","id":"52525b1bd2b68b00020006c5"},"asset_id":"514a25a30f7ca625870000b9","bounds":{"width":"0.6680440771349863","height":"0.013723696248856358","x":"0.12258953168044077","y":"0.5580969807868252"},"data":{"character":"Helen West","description":"","actor":"Grace Tyson"},"entity_id":"510feb5ac44ecc000200000c","created_at":"2013-10-07T09:13:13Z"},{"id":"525ffc10ad1f4c000202690a","user":{"name":"User.525ff191ad1f4c0002000225","id":"525ff191ad1f4c0002000225"},"asset_id":"514a25a30f7ca625870000b9","bounds":{"width":"0.7460526315789474","height":"0.02096069868995633","x":"0.08552631578947368","y":"0.5545851528384279"},"data":{"character":"Helen West","description":"","actor":"Grace Tyson"},"entity_id":"510feb5ac44ecc000200000c","created_at":"2013-10-17T15:02:40Z"}]},{"name":"Cast Member","entity_id":"510feb5ac44ecc000200000c","confidence":"low","asset_id":"514a25a30f7ca625870000b9","bounds":{"width":"0.6680440771349863","height":"0.01463860933211345","x":"0.12258953168044077","y":"0.494967978042086"},"data":{"character":{"value":"Celia West","confidence":"low"},"description":{"value":"","confidence":"low"},"actor":{"value":"Anna Laughlin","confidence":"low"}},"revisions":[{"id":"52527b2959df600002005893","user":{"name":"User.52525b1bd2b68b00020006c5","id":"52525b1bd2b68b00020006c5"},"asset_id":"514a25a30f7ca625870000b9","bounds":{"width":"0.6680440771349863","height":"0.01463860933211345","x":"0.12258953168044077","y":"0.494967978042086"},"data":{"character":"Celia West","description":"","actor":"Anna Laughlin"},"entity_id":"510feb5ac44ecc000200000c","created_at":"2013-10-07T09:13:13Z"}]},{"name":"Cast Member","entity_id":"510feb5ac44ecc000200000c","confidence":"low","asset_id":"514a25a30f7ca625870000b9","bounds":{"width":"0.6707988980716253","height":"0.01555352241537054","x":"0.11983471074380166","y":"0.5773101555352241"},"data":{"character":{"value":"Ann","confidence":"low"},"description":{"value":"the cook","confidence":"medium"},"actor":{"value":"Sallie Stembler","confidence":"medium"}},"revisions":[{"id":"52527b2959df600002005891","user":{"name":"User.52525b1bd2b68b00020006c5","id":"52525b1bd2b68b00020006c5"},"asset_id":"514a25a30f7ca625870000b9","bounds":{"width":"0.6707988980716253","height":"0.01555352241537054","x":"0.11983471074380166","y":"0.5773101555352241"},"data":{"character":"Ann","description":"the cook","actor":"Sallie Stembler"},"entity_id":"510feb5ac44ecc000200000c","created_at":"2013-10-07T09:13:13Z"},{"id":"525ffc10ad1f4c000202690c","user":{"name":"User.525ff191ad1f4c0002000225","id":"525ff191ad1f4c0002000225"},"asset_id":"514a25a30f7ca625870000b9","bounds":{"width":"0.7342105263157894","height":"0.01834061135371179","x":"0.08421052631578947","y":"0.5790393013100437"},"data":{"character":"Ann ","description":"the cook","actor":"Sallie Stembler"},"entity_id":"510feb5ac44ecc000200000c","created_at":"2013-10-17T15:02:40Z"}]},{"name":"Cast Member","entity_id":"510feb5ac44ecc000200000c","confidence":"medium","asset_id":"514a25a30f7ca625870000b9","bounds":{"width":"0.6694214876033058","height":"0.01463860933211345","x":"0.12258953168044077","y":"0.5361390667886551"},"data":{"character":{"value":"Fred West","confidence":"medium"},"description":{"value":"","confidence":"medium"},"actor":{"value":"Arthur McWatters","confidence":"medium"}},"revisions":[{"id":"52527b2959df60000200588f","user":{"name":"User.52525b1bd2b68b00020006c5","id":"52525b1bd2b68b00020006c5"},"asset_id":"514a25a30f7ca625870000b9","bounds":{"width":"0.6694214876033058","height":"0.01463860933211345","x":"0.12258953168044077","y":"0.5361390667886551"},"data":{"character":"Fred West","description":"","actor":"Arthur McWatters"},"entity_id":"510feb5ac44ecc000200000c","created_at":"2013-10-07T09:13:13Z"},{"id":"525ffc10ad1f4c0002026908","user":{"name":"User.525ff191ad1f4c0002000225","id":"525ff191ad1f4c0002000225"},"asset_id":"514a25a30f7ca625870000b9","bounds":{"width":"0.7236842105263158","height":"0.01834061135371179","x":"0.09078947368421053","y":"0.5353711790393013"},"data":{"character":"Fred West","description":"","actor":"Arthur McWatters"},"entity_id":"510feb5ac44ecc000200000c","created_at":"2013-10-17T15:02:40Z"}]},{"name":"Cast Member","entity_id":"510feb5ac44ecc000200000c","confidence":"medium","asset_id":"514a25a30f7ca625870000b9","bounds":{"width":"0.6680440771349863","height":"0.013723696248856358","x":"0.12258953168044077","y":"0.5169258920402562"},"data":{"character":{"value":"Carrie Beverly","confidence":"medium"},"description":{"value":"","confidence":"medium"},"actor":{"value":"Louise Mink","confidence":"medium"}},"revisions":[{"id":"52527b2959df60000200588d","user":{"name":"User.52525b1bd2b68b00020006c5","id":"52525b1bd2b68b00020006c5"},"asset_id":"514a25a30f7ca625870000b9","bounds":{"width":"0.6680440771349863","height":"0.013723696248856358","x":"0.12258953168044077","y":"0.5169258920402562"},"data":{"character":"Carrie Beverly","description":"","actor":"Louise Mink"},"entity_id":"510feb5ac44ecc000200000c","created_at":"2013-10-07T09:13:13Z"},{"id":"525ffc10ad1f4c0002026906","user":{"name":"User.525ff191ad1f4c0002000225","id":"525ff191ad1f4c0002000225"},"asset_id":"514a25a30f7ca625870000b9","bounds":{"width":"0.7460526315789474","height":"0.02096069868995633","x":"0.08421052631578947","y":"0.514410480349345"},"data":{"character":"Carrie Beverly","description":"","actor":"Louise Mink"},"entity_id":"510feb5ac44ecc000200000c","created_at":"2013-10-17T15:02:40Z"}]},{"name":"Cast Member","entity_id":"510feb5ac44ecc000200000c","confidence":"low","asset_id":"514a25a30f7ca625870000b9","bounds":{"width":"0.6707988980716253","height":"0.01463860933211345","x":"0.11983471074380166","y":"0.4730100640439158"},"data":{"character":{"value":"Spaff Hyman","confidence":"low"},"description":{"value":"","confidence":"low"},"actor":{"value":"Will J. Kennedy","confidence":"low"}},"revisions":[{"id":"52527b2959df60000200588b","user":{"name":"User.52525b1bd2b68b00020006c5","id":"52525b1bd2b68b00020006c5"},"asset_id":"514a25a30f7ca625870000b9","bounds":{"width":"0.6707988980716253","height":"0.01463860933211345","x":"0.11983471074380166","y":"0.4730100640439158"},"data":{"character":"Spaff Hyman","description":"","actor":"Will J. Kennedy"},"entity_id":"510feb5ac44ecc000200000c","created_at":"2013-10-07T09:13:13Z"}]},{"name":"Cast Member","entity_id":"510feb5ac44ecc000200000c","confidence":"medium","asset_id":"514a25a30f7ca625870000b9","bounds":{"width":"0.6735537190082644","height":"0.025617566331198535","x":"0.12121212121212122","y":"0.5910338517840805"},"data":{"character":{"value":"Professor Ivory","confidence":"medium"},"description":{"value":"","confidence":"medium"},"actor":{"value":"Albert Hart","confidence":"medium"}},"revisions":[{"id":"52527b2959df600002005897","user":{"name":"User.52525b1bd2b68b00020006c5","id":"52525b1bd2b68b00020006c5"},"asset_id":"514a25a30f7ca625870000b9","bounds":{"width":"0.6735537190082644","height":"0.025617566331198535","x":"0.12121212121212122","y":"0.5910338517840805"},"data":{"character":"Professor Ivory","description":"","actor":"Albert Hart"},"entity_id":"510feb5ac44ecc000200000c","created_at":"2013-10-07T09:13:13Z"},{"id":"525ffc10ad1f4c000202690e","user":{"name":"User.525ff191ad1f4c0002000225","id":"525ff191ad1f4c0002000225"},"asset_id":"514a25a30f7ca625870000b9","bounds":{"width":"0.7026315789473684","height":"0.034934497816593885","x":"0.10921052631578948","y":"0.5807860262008734"},"data":{"character":"Professor Ivory","description":"","actor":"Albert Hart"},"entity_id":"510feb5ac44ecc000200000c","created_at":"2013-10-17T15:02:40Z"}]},{"name":"Cast Member","entity_id":"510feb5ac44ecc000200000c","confidence":"medium","asset_id":"514a25a30f7ca625870000b9","bounds":{"width":"0.6749311294765841","height":"0.021043000914913082","x":"0.11983471074380166","y":"0.616651418115279"},"data":{"character":{"value":"Lawrence McManus","confidence":"medium"},"description":{"value":"","confidence":"medium"},"actor":{"value":"Junie McCree","confidence":"medium"}},"revisions":[{"id":"52527b2959df60000200589f","user":{"name":"User.52525b1bd2b68b00020006c5","id":"52525b1bd2b68b00020006c5"},"asset_id":"514a25a30f7ca625870000b9","bounds":{"width":"0.6749311294765841","height":"0.021043000914913082","x":"0.11983471074380166","y":"0.616651418115279"},"data":{"character":"Lawrence McManus","description":"","actor":"Junie McCree"},"entity_id":"510feb5ac44ecc000200000c","created_at":"2013-10-07T09:13:13Z"},{"id":"525ffc10ad1f4c0002026910","user":{"name":"User.525ff191ad1f4c0002000225","id":"525ff191ad1f4c0002000225"},"asset_id":"514a25a30f7ca625870000b9","bounds":{"width":"0.7026315789473684","height":"0.017467248908296942","x":"0.10657894736842105","y":"0.6192139737991267"},"data":{"character":"Lawrence McManus","description":"","actor":"Junie McCree"},"entity_id":"510feb5ac44ecc000200000c","created_at":"2013-10-17T15:02:40Z"}]},{"name":"Cast Member","entity_id":"510feb5ac44ecc000200000c","confidence":"low","asset_id":"514a25a30f7ca625870000b9","bounds":{"width":"0.7131578947368421","height":"0.11353711790393013","x":"0.10394736842105263","y":"0.6532751091703056"},"data":{"character":{"value":"a \"Little Fawn\"","confidence":"high"},"description":{"value":"","confidence":"high"},"actor":{"value":"Marjorie Cogan","confidence":"low"}},"revisions":[{"id":"525ffc10ad1f4c0002026934","user":{"name":"User.525ff191ad1f4c0002000225","id":"525ff191ad1f4c0002000225"},"asset_id":"514a25a30f7ca625870000b9","bounds":{"width":"0.7131578947368421","height":"0.11353711790393013","x":"0.10394736842105263","y":"0.6532751091703056"},"data":{"character":"a \"Little Fawn\"","description":"","actor":"Marjorie Cogan"},"entity_id":"510feb5ac44ecc000200000c","created_at":"2013-10-17T15:02:40Z"},{"id":"525ffc10ad1f4c0002026936","user":{"name":"User.525ff191ad1f4c0002000225","id":"525ff191ad1f4c0002000225"},"asset_id":"514a25a30f7ca625870000b9","bounds":{"width":"0.7052631578947368","height":"0.1091703056768559","x":"0.11447368421052631","y":"0.6558951965065503"},"data":{"character":"a \"Little Fawn\"","description":"","actor":"Alice Clifford"},"entity_id":"510feb5ac44ecc000200000c","created_at":"2013-10-17T15:02:40Z"},{"id":"525ffc10ad1f4c000202693c","user":{"name":"User.525ff191ad1f4c0002000225","id":"525ff191ad1f4c0002000225"},"asset_id":"514a25a30f7ca625870000b9","bounds":{"width":"0.7197368421052631","height":"0.13362445414847163","x":"0.10526315789473683","y":"0.6375545851528385"},"data":{"character":"a \"Little Fawn\"","description":"","actor":"Millie Lorraine"},"entity_id":"510feb5ac44ecc000200000c","created_at":"2013-10-17T15:02:40Z"},{"id":"525ffc10ad1f4c000202693e","user":{"name":"User.525ff191ad1f4c0002000225","id":"525ff191ad1f4c0002000225"},"asset_id":"514a25a30f7ca625870000b9","bounds":{"width":"0.7289473684210527","height":"0.1388646288209607","x":"0.1","y":"0.6358078602620087"},"data":{"character":"a \"Little Fawn\"","description":"","actor":"Anna Sayce"},"entity_id":"510feb5ac44ecc000200000c","created_at":"2013-10-17T15:02:40Z"},{"id":"525ffc10ad1f4c0002026942","user":{"name":"User.525ff191ad1f4c0002000225","id":"525ff191ad1f4c0002000225"},"asset_id":"514a25a30f7ca625870000b9","bounds":{"width":"0.7131578947368421","height":"0.14410480349344978","x":"0.1118421052631579","y":"0.6296943231441048"},"data":{"character":"a \"Little Fawn\"","description":"","actor":"Cissie Shatten"},"entity_id":"510feb5ac44ecc000200000c","created_at":"2013-10-17T15:02:40Z"},{"id":"525ffc10ad1f4c000202693a","user":{"name":"User.525ff191ad1f4c0002000225","id":"525ff191ad1f4c0002000225"},"asset_id":"514a25a30f7ca625870000b9","bounds":{"width":"0.7342105263157894","height":"0.12925764192139738","x":"0.09078947368421053","y":"0.640174672489083"},"data":{"character":"a \"Little Fawn\"","description":"","actor":"Mittie Bright"},"entity_id":"510feb5ac44ecc000200000c","created_at":"2013-10-17T15:02:40Z"},{"id":"525ffc10ad1f4c0002026940","user":{"name":"User.525ff191ad1f4c0002000225","id":"525ff191ad1f4c0002000225"},"asset_id":"514a25a30f7ca625870000b9","bounds":{"width":"0.7289473684210527","height":"0.1406113537117904","x":"0.09473684210526316","y":"0.6314410480349345"},"data":{"character":"a \"Little Fawn\"","description":"","actor":"Frances Alaine"},"entity_id":"510feb5ac44ecc000200000c","created_at":"2013-10-17T15:02:40Z"},{"id":"525ffc10ad1f4c000202692c","user":{"name":"User.525ff191ad1f4c0002000225","id":"525ff191ad1f4c0002000225"},"asset_id":"514a25a30f7ca625870000b9","bounds":{"width":"0.7092105263157895","height":"0.11528384279475982","x":"0.10263157894736842","y":"0.645414847161572"},"data":{"character":"a \"Little Fawn\"","description":"","actor":"Nettie Hamilton"},"entity_id":"510feb5ac44ecc000200000c","created_at":"2013-10-17T15:02:40Z"},{"id":"525ffc10ad1f4c0002026938","user":{"name":"User.525ff191ad1f4c0002000225","id":"525ff191ad1f4c0002000225"},"asset_id":"514a25a30f7ca625870000b9","bounds":{"width":"0.7210526315789474","height":"0.14410480349344978","x":"0.09473684210526316","y":"0.6244541484716157"},"data":{"character":"a \"Little Fawn\"","description":"","actor":"Helen Luchs"},"entity_id":"510feb5ac44ecc000200000c","created_at":"2013-10-17T15:02:40Z"},{"id":"525ffc10ad1f4c0002026932","user":{"name":"User.525ff191ad1f4c0002000225","id":"525ff191ad1f4c0002000225"},"asset_id":"514a25a30f7ca625870000b9","bounds":{"width":"0.7131578947368421","height":"0.13362445414847163","x":"0.10526315789473683","y":"0.6349344978165938"},"data":{"character":"a \"Little Fawn\"","description":"","actor":"Fannie Bradshaw"},"entity_id":"510feb5ac44ecc000200000c","created_at":"2013-10-17T15:02:40Z"},{"id":"525ffc10ad1f4c0002026928","user":{"name":"User.525ff191ad1f4c0002000225","id":"525ff191ad1f4c0002000225"},"asset_id":"514a25a30f7ca625870000b9","bounds":{"width":"0.7342105263157894","height":"0.07598253275109171","x":"0.07368421052631578","y":"0.6873362445414847"},"data":{"character":"a \"Little Fawn\"","description":"","actor":"Vera DeFord"},"entity_id":"510feb5ac44ecc000200000c","created_at":"2013-10-17T15:02:40Z"},{"id":"525ffc10ad1f4c0002026926","user":{"name":"User.525ff191ad1f4c0002000225","id":"525ff191ad1f4c0002000225"},"asset_id":"514a25a30f7ca625870000b9","bounds":{"width":"0.7197368421052631","height":"0.07860262008733625","x":"0.08026315789473684","y":"0.6777292576419214"},"data":{"character":"a \"Little Fawn\"","description":"","actor":"Miriam Sanford"},"entity_id":"510feb5ac44ecc000200000c","created_at":"2013-10-17T15:02:40Z"},{"id":"525ffc10ad1f4c0002026924","user":{"name":"User.525ff191ad1f4c0002000225","id":"525ff191ad1f4c0002000225"},"asset_id":"514a25a30f7ca625870000b9","bounds":{"width":"0.6960526315789474","height":"0.06899563318777292","x":"0.09736842105263157","y":"0.6917030567685589"},"data":{"character":"a \"Little Fawn\"","description":"","actor":"Margaret Taylor"},"entity_id":"510feb5ac44ecc000200000c","created_at":"2013-10-17T15:02:40Z"},{"id":"525ffc10ad1f4c000202692e","user":{"name":"User.525ff191ad1f4c0002000225","id":"525ff191ad1f4c0002000225"},"asset_id":"514a25a30f7ca625870000b9","bounds":{"width":"0.7092105263157895","height":"0.1205240174672489","x":"0.10789473684210526","y":"0.645414847161572"},"data":{"character":"a \"Little Fawn\"","description":"","actor":"Lew Page"},"entity_id":"510feb5ac44ecc000200000c","created_at":"2013-10-17T15:02:40Z"},{"id":"525ffc10ad1f4c0002026930","user":{"name":"User.525ff191ad1f4c0002000225","id":"525ff191ad1f4c0002000225"},"asset_id":"514a25a30f7ca625870000b9","bounds":{"width":"0.7131578947368421","height":"0.11790393013100436","x":"0.10789473684210526","y":"0.6489082969432315"},"data":{"character":"a \"Little Fawn\"","description":"","actor":"Rita Mason"},"entity_id":"510feb5ac44ecc000200000c","created_at":"2013-10-17T15:02:40Z"},{"id":"525ffc10ad1f4c000202692a","user":{"name":"User.525ff191ad1f4c0002000225","id":"525ff191ad1f4c0002000225"},"asset_id":"514a25a30f7ca625870000b9","bounds":{"width":"0.7144736842105263","height":"0.09868995633187773","x":"0.09605263157894736","y":"0.662882096069869"},"data":{"character":"a \"Little Fawn\"","description":"","actor":"Edna Ford"},"entity_id":"510feb5ac44ecc000200000c","created_at":"2013-10-17T15:02:40Z"}]},{"name":"Cast Member","entity_id":"510feb5ac44ecc000200000c","confidence":"low","asset_id":"514a25a30f7ca625870000b9","bounds":{"width":"0.6855263157894736","height":"0.03318777292576419","x":"0.10789473684210526","y":"0.6611353711790393"},"data":{"character":{"value":"\"Athletic Girl\"","confidence":"high"},"description":{"value":"","confidence":"high"},"actor":{"value":"Lethia Gray","confidence":"low"}},"revisions":[{"id":"525ffc10ad1f4c0002026914","user":{"name":"User.525ff191ad1f4c0002000225","id":"525ff191ad1f4c0002000225"},"asset_id":"514a25a30f7ca625870000b9","bounds":{"width":"0.6855263157894736","height":"0.03318777292576419","x":"0.10789473684210526","y":"0.6611353711790393"},"data":{"character":"\"Athletic Girl\"","description":"","actor":"Lethia Gray"},"entity_id":"510feb5ac44ecc000200000c","created_at":"2013-10-17T15:02:40Z"},{"id":"525ffc10ad1f4c0002026918","user":{"name":"User.525ff191ad1f4c0002000225","id":"525ff191ad1f4c0002000225"},"asset_id":"514a25a30f7ca625870000b9","bounds":{"width":"0.7105263157894737","height":"0.043668122270742356","x":"0.0881578947368421","y":"0.6497816593886463"},"data":{"character":"\"Athletic Girl\"","description":"","actor":"Martha Dean"},"entity_id":"510feb5ac44ecc000200000c","created_at":"2013-10-17T15:02:40Z"},{"id":"525ffc10ad1f4c0002026922","user":{"name":"User.525ff191ad1f4c0002000225","id":"525ff191ad1f4c0002000225"},"asset_id":"514a25a30f7ca625870000b9","bounds":{"width":"0.6894736842105263","height":"0.07161572052401746","x":"0.10789473684210526","y":"0.6296943231441048"},"data":{"character":"\"Athletic Girl\"","description":"","actor":"Minnie Monroe "},"entity_id":"510feb5ac44ecc000200000c","created_at":"2013-10-17T15:02:40Z"},{"id":"525ffc10ad1f4c000202691e","user":{"name":"User.525ff191ad1f4c0002000225","id":"525ff191ad1f4c0002000225"},"asset_id":"514a25a30f7ca625870000b9","bounds":{"width":"0.6789473684210526","height":"0.048034934497816595","x":"0.11973684210526315","y":"0.651528384279476"},"data":{"character":"\"Athletic Girl\"","description":"","actor":"Betty Scott"},"entity_id":"510feb5ac44ecc000200000c","created_at":"2013-10-17T15:02:40Z"},{"id":"525ffc10ad1f4c000202691a","user":{"name":"User.525ff191ad1f4c0002000225","id":"525ff191ad1f4c0002000225"},"asset_id":"514a25a30f7ca625870000b9","bounds":{"width":"0.6815789473684211","height":"0.05414847161572053","x":"0.11447368421052631","y":"0.6445414847161572"},"data":{"character":"\"Athletic Girl\"","description":"","actor":"Billie West"},"entity_id":"510feb5ac44ecc000200000c","created_at":"2013-10-17T15:02:40Z"},{"id":"525ffc10ad1f4c000202691c","user":{"name":"User.525ff191ad1f4c0002000225","id":"525ff191ad1f4c0002000225"},"asset_id":"514a25a30f7ca625870000b9","bounds":{"width":"0.7210526315789474","height":"0.06724890829694323","x":"0.08026315789473684","y":"0.6349344978165938"},"data":{"character":"\"Athletic Girl\"","description":"","actor":"Katheryn Beach"},"entity_id":"510feb5ac44ecc000200000c","created_at":"2013-10-17T15:02:40Z"},{"id":"525ffc10ad1f4c0002026916","user":{"name":"User.525ff191ad1f4c0002000225","id":"525ff191ad1f4c0002000225"},"asset_id":"514a25a30f7ca625870000b9","bounds":{"width":"0.7","height":"0.04017467248908297","x":"0.09868421052631579","y":"0.6541484716157205"},"data":{"character":"\"Athletic Girl\"","description":"","actor":"Lea LeLand"},"entity_id":"510feb5ac44ecc000200000c","created_at":"2013-10-17T15:02:40Z"}]},{"name":"Cast Member","entity_id":"510feb5ac44ecc000200000c","confidence":"low","asset_id":"514a25a30f7ca625870000b9","bounds":{"width":"0.6934210526315789","height":"0.07423580786026201","x":"0.1118421052631579","y":"0.6305676855895197"},"data":{"character":{"value":"\"Athletic Girl\"","confidence":"low"},"description":{"value":"","confidence":"low"},"actor":{"value":"Cecile Mayo","confidence":"low"}},"revisions":[{"id":"525ffc10ad1f4c0002026920","user":{"name":"User.525ff191ad1f4c0002000225","id":"525ff191ad1f4c0002000225"},"asset_id":"514a25a30f7ca625870000b9","bounds":{"width":"0.6934210526315789","height":"0.07423580786026201","x":"0.1118421052631579","y":"0.6305676855895197"},"data":{"character":"\"Athletic Girl\"","description":"","actor":"Cecile Mayo"},"entity_id":"510feb5ac44ecc000200000c","created_at":"2013-10-17T15:02:40Z"}]},{"name":"Cast Member","entity_id":"510feb5ac44ecc000200000c","confidence":"low","asset_id":"514a25a30f7ca625870000b9","bounds":{"width":"0.7","height":"0.022707423580786028","x":"0.10921052631578948","y":"0.47510917030567684"},"data":{"character":{"value":"Spaff Hyman","confidence":"low"},"description":{"value":"","confidence":"low"},"actor":{"value":"Will J. Kennedy","confidence":"low"}},"revisions":[{"id":"525ffc10ad1f4c0002026902","user":{"name":"User.525ff191ad1f4c0002000225","id":"525ff191ad1f4c0002000225"},"asset_id":"514a25a30f7ca625870000b9","bounds":{"width":"0.7","height":"0.022707423580786028","x":"0.10921052631578948","y":"0.47510917030567684"},"data":{"character":"Spaff Hyman","description":"","actor":"Will J. Kennedy"},"entity_id":"510feb5ac44ecc000200000c","created_at":"2013-10-17T15:02:40Z"}]},{"name":"Cast Member","entity_id":"510feb5ac44ecc000200000c","confidence":"low","asset_id":"514a25a30f7ca625870000b9","bounds":{"width":"0.7144736842105263","height":"0.02794759825327511","x":"0.09736842105263157","y":"0.48384279475982533"},"data":{"character":{"value":"Celia West","confidence":"low"},"description":{"value":"","confidence":"low"},"actor":{"value":"Anna Laughlin","confidence":"low"}},"revisions":[{"id":"525ffc10ad1f4c0002026904","user":{"name":"User.525ff191ad1f4c0002000225","id":"525ff191ad1f4c0002000225"},"asset_id":"514a25a30f7ca625870000b9","bounds":{"width":"0.7144736842105263","height":"0.02794759825327511","x":"0.09736842105263157","y":"0.48384279475982533"},"data":{"character":"Celia West","description":"","actor":"Anna Laughlin"},"entity_id":"510feb5ac44ecc000200000c","created_at":"2013-10-17T15:02:40Z"}]},{"name":"Production Staff","entity_id":"510feb5ac44ecc0002000010","confidence":"low","asset_id":"514a25a30f7ca625870000b9","bounds":{"width":"0.23140495867768596","height":"0.018298261665141813","x":"0.19972451790633608","y":"0.40530649588289114"},"data":{"role":{"value":"Music","confidence":"low"},"name":{"value":"Hans S. Linne","confidence":"medium"}},"revisions":[{"id":"52527b2959df60000200589b","user":{"name":"User.52525b1bd2b68b00020006c5","id":"52525b1bd2b68b00020006c5"},"asset_id":"514a25a30f7ca625870000b9","bounds":{"width":"0.23140495867768596","height":"0.018298261665141813","x":"0.19972451790633608","y":"0.40530649588289114"},"data":{"role":"Music","name":"Hans S. Linne"},"entity_id":"510feb5ac44ecc0002000010","created_at":"2013-10-07T09:13:13Z"},{"id":"525ffc10ad1f4c00020268fe","user":{"name":"User.525ff191ad1f4c0002000225","id":"525ff191ad1f4c0002000225"},"asset_id":"514a25a30f7ca625870000b9","bounds":{"width":"0.23684210526315788","height":"0.017467248908296942","x":"0.2","y":"0.40611353711790393"},"data":{"role":"Composer","name":"Hans S. Linne"},"entity_id":"510feb5ac44ecc0002000010","created_at":"2013-10-17T15:02:40Z"}]},{"name":"Production Staff","entity_id":"510feb5ac44ecc0002000010","confidence":"low","asset_id":"514a25a30f7ca625870000b9","bounds":{"width":"0.31955922865013775","height":"0.0292772186642269","x":"0.3953168044077135","y":"0.40988106129917656"},"data":{"role":{"value":"additional numbers by","confidence":"low"},"name":{"value":"Will H. Becker","confidence":"low"}},"revisions":[{"id":"52527b2959df60000200589d","user":{"name":"User.52525b1bd2b68b00020006c5","id":"52525b1bd2b68b00020006c5"},"asset_id":"514a25a30f7ca625870000b9","bounds":{"width":"0.31955922865013775","height":"0.0292772186642269","x":"0.3953168044077135","y":"0.40988106129917656"},"data":{"role":"additional numbers by","name":"Will H. Becker"},"entity_id":"510feb5ac44ecc0002000010","created_at":"2013-10-07T09:13:13Z"}]},{"name":"Production Staff","entity_id":"510feb5ac44ecc0002000010","confidence":"low","asset_id":"514a25a30f7ca625870000b9","bounds":{"width":"0.3787878787878788","height":"0.011893870082342177","x":"0.26859504132231404","y":"0.38609332113449224"},"data":{"role":{"value":"Adaptation and Lyrics","confidence":"low"},"name":{"value":"Junie McCree","confidence":"medium"}},"revisions":[{"id":"52527b2959df600002005899","user":{"name":"User.52525b1bd2b68b00020006c5","id":"52525b1bd2b68b00020006c5"},"asset_id":"514a25a30f7ca625870000b9","bounds":{"width":"0.3787878787878788","height":"0.011893870082342177","x":"0.26859504132231404","y":"0.38609332113449224"},"data":{"role":"Adaptation and Lyrics","name":"Junie McCree"},"entity_id":"510feb5ac44ecc0002000010","created_at":"2013-10-07T09:13:13Z"},{"id":"525ffc10ad1f4c00020268fc","user":{"name":"User.525ff191ad1f4c0002000225","id":"525ff191ad1f4c0002000225"},"asset_id":"514a25a30f7ca625870000b9","bounds":{"width":"0.37894736842105264","height":"0.01222707423580786","x":"0.26842105263157895","y":"0.3860262008733624"},"data":{"role":"Adaptor and Lyricist","name":"Junie McCree"},"entity_id":"510feb5ac44ecc0002000010","created_at":"2013-10-17T15:02:40Z"}]},{"name":"Production Staff","entity_id":"510feb5ac44ecc0002000010","confidence":"low","asset_id":"514a25c00f7ca625870000c3","bounds":{"width":"0.6697368421052632","height":"0.028896672504378284","x":"0.13026315789473683","y":"0.37302977232924694"},"data":{"role":{"value":"Manager, Lederer's Costume Department","confidence":"low"},"name":{"value":"Mrs. Kate Keeler","confidence":"low"}},"revisions":[{"id":"525ffc11ad1f4c0002026990","user":{"name":"User.525ff191ad1f4c0002000225","id":"525ff191ad1f4c0002000225"},"asset_id":"514a25c00f7ca625870000c3","bounds":{"width":"0.6697368421052632","height":"0.028896672504378284","x":"0.13026315789473683","y":"0.37302977232924694"},"data":{"role":"Manager, Lederer's Costume Department","name":"Mrs. Kate Keeler"},"entity_id":"510feb5ac44ecc0002000010","created_at":"2013-10-17T15:02:41Z"}]},{"name":"Production Staff","entity_id":"510feb5ac44ecc0002000010","confidence":"low","asset_id":"514a25c00f7ca625870000c3","bounds":{"width":"0.5460526315789473","height":"0.03239929947460595","x":"0.15657894736842104","y":"0.3476357267950963"},"data":{"role":{"value":"Choreographer","confidence":"low"},"name":{"value":"Julian Alfred","confidence":"low"}},"revisions":[{"id":"525ffc11ad1f4c000202698e","user":{"name":"User.525ff191ad1f4c0002000225","id":"525ff191ad1f4c0002000225"},"asset_id":"514a25c00f7ca625870000c3","bounds":{"width":"0.5460526315789473","height":"0.03239929947460595","x":"0.15657894736842104","y":"0.3476357267950963"},"data":{"role":"Choreographer","name":"Julian Alfred"},"entity_id":"510feb5ac44ecc0002000010","created_at":"2013-10-17T15:02:41Z"},{"id":"525ffc11ad1f4c000202698c","user":{"name":"User.525ff191ad1f4c0002000225","id":"525ff191ad1f4c0002000225"},"asset_id":"514a25c00f7ca625870000c3","bounds":{"width":"0.5907894736842105","height":"0.020140105078809107","x":"0.16842105263157894","y":"0.3476357267950963"},"data":{"role":"Conductor and Composer","name":"Hans S. Linne"},"entity_id":"510feb5ac44ecc0002000010","created_at":"2013-10-17T15:02:41Z"}]},{"name":"Production Staff","entity_id":"510feb5ac44ecc0002000010","confidence":"low","asset_id":"514a25a30f7ca625870000b9","bounds":{"width":"0.29605263157894734","height":"0.011353711790393014","x":"0.3092105263157895","y":"0.27336244541484716"},"data":{"role":{"value":"Producer","confidence":"low"},"name":{"value":"George W. Lederer","confidence":"low"}},"revisions":[{"id":"525ffc10ad1f4c00020268f6","user":{"name":"User.525ff191ad1f4c0002000225","id":"525ff191ad1f4c0002000225"},"asset_id":"514a25a30f7ca625870000b9","bounds":{"width":"0.29605263157894734","height":"0.011353711790393014","x":"0.3092105263157895","y":"0.27336244541484716"},"data":{"role":"Producer","name":"George W. Lederer"},"entity_id":"510feb5ac44ecc0002000010","created_at":"2013-10-17T15:02:40Z"}]},{"name":"Production Staff","entity_id":"510feb5ac44ecc0002000010","confidence":"low","asset_id":"514a25a30f7ca625870000b9","bounds":{"width":"0.5684210526315789","height":"0.0462882096069869","x":"0.17763157894736842","y":"0.3982532751091703"},"data":{"role":{"value":"Composer","confidence":"low"},"name":{"value":"Will H. Becker","confidence":"low"}},"revisions":[{"id":"525ffc10ad1f4c0002026900","user":{"name":"User.525ff191ad1f4c0002000225","id":"525ff191ad1f4c0002000225"},"asset_id":"514a25a30f7ca625870000b9","bounds":{"width":"0.5684210526315789","height":"0.0462882096069869","x":"0.17763157894736842","y":"0.3982532751091703"},"data":{"role":"Composer","name":"Will H. Becker"},"entity_id":"510feb5ac44ecc0002000010","created_at":"2013-10-17T15:02:40Z"}]},{"name":"Production Staff","entity_id":"510feb5ac44ecc0002000010","confidence":"low","asset_id":"514a25c00f7ca625870000c3","bounds":{"width":"0.4710526315789474","height":"0.040280210157618214","x":"0.22763157894736843","y":"0.3126094570928196"},"data":{"role":{"value":"Scenery Builder","confidence":"low"},"name":{"value":"Samuel Friedman","confidence":"low"}},"revisions":[{"id":"525ffc11ad1f4c000202698a","user":{"name":"User.525ff191ad1f4c0002000225","id":"525ff191ad1f4c0002000225"},"asset_id":"514a25c00f7ca625870000c3","bounds":{"width":"0.4710526315789474","height":"0.040280210157618214","x":"0.22763157894736843","y":"0.3126094570928196"},"data":{"role":"Scenery Builder","name":"Samuel Friedman"},"entity_id":"510feb5ac44ecc0002000010","created_at":"2013-10-17T15:02:41Z"}]},{"name":"Location","entity_id":"510feb5ac44ecc000200000a","confidence":"medium","asset_id":"514a25a30f7ca625870000b9","bounds":{"width":"0.4090909090909091","height":"0.022872827081427266","x":"0.24517906336088155","y":"0.1637694419030192"},"data":{"location":{"value":"Broadway, at Forty-First Street","confidence":"medium"}},"revisions":[{"id":"52527b2959df600002005889","user":{"name":"User.52525b1bd2b68b00020006c5","id":"52525b1bd2b68b00020006c5"},"asset_id":"514a25a30f7ca625870000b9","bounds":{"width":"0.4090909090909091","height":"0.022872827081427266","x":"0.24517906336088155","y":"0.1637694419030192"},"data":{"location":"Broadway, at Forty-First Street"},"entity_id":"510feb5ac44ecc000200000a","created_at":"2013-10-07T09:13:13Z"},{"id":"525ffc0fad1f4c00020268f2","user":{"name":"User.525ff191ad1f4c0002000225","id":"525ff191ad1f4c0002000225"},"asset_id":"514a25a30f7ca625870000b9","bounds":{"width":"0.4381578947368421","height":"0.017467248908296942","x":"0.23421052631578948","y":"0.16244541484716157"},"data":{"location":"Broadway, at Forty-First Street"},"entity_id":"510feb5ac44ecc000200000a","created_at":"2013-10-17T15:02:39Z"}]},{"name":"Theater Name","entity_id":"510feb5ac44ecc0002000008","confidence":"medium","asset_id":"514a25a30f7ca625870000b9","bounds":{"width":"0.8663911845730028","height":"0.11985361390667887","x":"0.02066115702479339","y":"0.03751143641354071"},"data":{"theater":{"value":"Broadway Theatre","confidence":"medium"}},"revisions":[{"id":"52527b2959df600002005887","user":{"name":"User.52525b1bd2b68b00020006c5","id":"52525b1bd2b68b00020006c5"},"asset_id":"514a25a30f7ca625870000b9","bounds":{"width":"0.8663911845730028","height":"0.11985361390667887","x":"0.02066115702479339","y":"0.03751143641354071"},"data":{"theater":"Broadway Theatre"},"entity_id":"510feb5ac44ecc0002000008","created_at":"2013-10-07T09:13:13Z"},{"id":"525ffc0fad1f4c00020268f0","user":{"name":"User.525ff191ad1f4c0002000225","id":"525ff191ad1f4c0002000225"},"asset_id":"514a25a30f7ca625870000b9","bounds":{"width":"0.8276315789473684","height":"0.10131004366812227","x":"0.04868421052631579","y":"0.032314410480349345"},"data":{"theater":"Broadway Theatre"},"entity_id":"510feb5ac44ecc0002000008","created_at":"2013-10-17T15:02:39Z"}]},{"name":"Show Date","entity_id":"510feb5ac44ecc0002000005","confidence":"medium","asset_id":"514a25a30f7ca625870000b9","bounds":{"width":"0.5647382920110193","height":"0.0192131747483989","x":"0.17768595041322313","y":"0.21866422689844464"},"data":{"date_opened":{"value":"05/27/1912","confidence":"medium"},"date_closed":{"value":"","confidence":"medium"}},"revisions":[{"id":"52527b2959df600002005885","user":{"name":"User.52525b1bd2b68b00020006c5","id":"52525b1bd2b68b00020006c5"},"asset_id":"514a25a30f7ca625870000b9","bounds":{"width":"0.5647382920110193","height":"0.0192131747483989","x":"0.17768595041322313","y":"0.21866422689844464"},"data":{"date_opened":"05/27/1912","date_closed":""},"entity_id":"510feb5ac44ecc0002000005","created_at":"2013-10-07T09:13:13Z"},{"id":"525ffc0fad1f4c00020268f4","user":{"name":"User.525ff191ad1f4c0002000225","id":"525ff191ad1f4c0002000225"},"asset_id":"514a25a30f7ca625870000b9","bounds":{"width":"0.5644736842105263","height":"0.01921397379912664","x":"0.17763157894736842","y":"0.2183406113537118"},"data":{"date_opened":"05/27/1912","date_closed":""},"entity_id":"510feb5ac44ecc0002000005","created_at":"2013-10-17T15:02:39Z"}]},{"name":"Show Title","entity_id":"510feb5ac44ecc0002000002","confidence":"medium","asset_id":"514a25a30f7ca625870000b9","bounds":{"width":"0.6873278236914601","height":"0.0384263494967978","x":"0.10330578512396695","y":"0.3110704483074108"},"data":{"title":{"value":"Mama's Baby Boy","confidence":"medium"},"type":{"value":"main title","confidence":"medium"}},"revisions":[{"id":"52527b2959df600002005883","user":{"name":"User.52525b1bd2b68b00020006c5","id":"52525b1bd2b68b00020006c5"},"asset_id":"514a25a30f7ca625870000b9","bounds":{"width":"0.6873278236914601","height":"0.0384263494967978","x":"0.10330578512396695","y":"0.3110704483074108"},"data":{"title":"Mama's Baby Boy","type":"main title"},"entity_id":"510feb5ac44ecc0002000002","created_at":"2013-10-07T09:13:13Z"},{"id":"525ffc10ad1f4c00020268f8","user":{"name":"User.525ff191ad1f4c0002000225","id":"525ff191ad1f4c0002000225"},"asset_id":"514a25a30f7ca625870000b9","bounds":{"width":"0.6881578947368421","height":"0.03842794759825328","x":"0.10263157894736842","y":"0.3109170305676856"},"data":{"title":"Mama's Baby Boy","type":"main title"},"entity_id":"510feb5ac44ecc0002000002","created_at":"2013-10-17T15:02:40Z"}]},{"name":"Show Title","entity_id":"510feb5ac44ecc0002000002","confidence":"low","asset_id":"514a25a30f7ca625870000b9","bounds":{"width":"0.29473684210526313","height":"0.010480349344978165","x":"0.3105263157894737","y":"0.36331877729257644"},"data":{"title":{"value":"A Musical Farce in Three Acts","confidence":"low"},"type":{"value":"subtitle","confidence":"low"}},"revisions":[{"id":"525ffc10ad1f4c00020268fa","user":{"name":"User.525ff191ad1f4c0002000225","id":"525ff191ad1f4c0002000225"},"asset_id":"514a25a30f7ca625870000b9","bounds":{"width":"0.29473684210526313","height":"0.010480349344978165","x":"0.3105263157894737","y":"0.36331877729257644"},"data":{"title":"A Musical Farce in Three Acts","type":"subtitle"},"entity_id":"510feb5ac44ecc0002000002","created_at":"2013-10-17T15:02:40Z"}]},{"name":"Advertisement","entity_id":"510feb5ac44ecc0002000013","confidence":"low","asset_id":"514a25ba0f7ca625870000c1","bounds":{"width":"0.7684210526315789","height":"0.09445407279029462","x":"0.06447368421052632","y":"0.8726169844020797"},"data":{"company":{"value":"St. James Importing Co., N. Y., Importers","confidence":"low"},"address":{"value":"","confidence":"low"},"goods":{"value":"Waw-Waw Sauce","confidence":"low"}},"revisions":[{"id":"525ffc11ad1f4c0002026982","user":{"name":"User.525ff191ad1f4c0002000225","id":"525ff191ad1f4c0002000225"},"asset_id":"514a25ba0f7ca625870000c1","bounds":{"width":"0.7684210526315789","height":"0.09445407279029462","x":"0.06447368421052632","y":"0.8726169844020797"},"data":{"company":"St. James Importing Co., N. Y., Importers","address":"","goods":"Waw-Waw Sauce"},"entity_id":"510feb5ac44ecc0002000013","created_at":"2013-10-17T15:02:41Z"}]},{"name":"Advertisement","entity_id":"510feb5ac44ecc0002000013","confidence":"low","asset_id":"514a25c00f7ca625870000c3","bounds":{"width":"0.618421052631579","height":"0.06042031523642732","x":"0.15394736842105264","y":"0.4343257443082312"},"data":{"company":{"value":"Sohmer & Co.","confidence":"low"},"address":{"value":"315 Fifth Avenue, Cor. 32d St., N. Y.","confidence":"low"},"goods":{"value":"pianos","confidence":"low"}},"revisions":[{"id":"525ffc11ad1f4c0002026992","user":{"name":"User.525ff191ad1f4c0002000225","id":"525ff191ad1f4c0002000225"},"asset_id":"514a25c00f7ca625870000c3","bounds":{"width":"0.618421052631579","height":"0.06042031523642732","x":"0.15394736842105264","y":"0.4343257443082312"},"data":{"company":"Sohmer & Co.","address":"315 Fifth Avenue, Cor. 32d St., N. Y.","goods":"pianos"},"entity_id":"510feb5ac44ecc0002000013","created_at":"2013-10-17T15:02:41Z"}]},{"name":"Advertisement","entity_id":"510feb5ac44ecc0002000013","confidence":"low","asset_id":"514a25b10f7ca625870000be","bounds":{"width":"0.7736842105263157","height":"0.05632582322357019","x":"0.11315789473684211","y":"0.6525129982668978"},"data":{"company":{"value":"Manhattan Cream Cheese","confidence":"low"},"address":{"value":"","confidence":"low"},"goods":{"value":"cream cheese","confidence":"low"}},"revisions":[{"id":"525ffc11ad1f4c000202696c","user":{"name":"User.525ff191ad1f4c0002000225","id":"525ff191ad1f4c0002000225"},"asset_id":"514a25b10f7ca625870000be","bounds":{"width":"0.7736842105263157","height":"0.05632582322357019","x":"0.11315789473684211","y":"0.6525129982668978"},"data":{"company":"Manhattan Cream Cheese","address":"","goods":"cream cheese"},"entity_id":"510feb5ac44ecc0002000013","created_at":"2013-10-17T15:02:41Z"}]},{"name":"Advertisement","entity_id":"510feb5ac44ecc0002000013","confidence":"low","asset_id":"514a25bd0f7ca625870000c2","bounds":{"width":"0.8315789473684211","height":"0.07005253940455341","x":"0.11315789473684211","y":"0.6085814360770578"},"data":{"company":{"value":"Elmsford Community","confidence":"low"},"address":{"value":"New York    ","confidence":"low"},"goods":{"value":"real estate auction","confidence":"low"}},"revisions":[{"id":"525ffc11ad1f4c0002026984","user":{"name":"User.525ff191ad1f4c0002000225","id":"525ff191ad1f4c0002000225"},"asset_id":"514a25bd0f7ca625870000c2","bounds":{"width":"0.8315789473684211","height":"0.07005253940455341","x":"0.11315789473684211","y":"0.6085814360770578"},"data":{"company":"Elmsford Community","address":"New York    ","goods":"real estate auction"},"entity_id":"510feb5ac44ecc0002000013","created_at":"2013-10-17T15:02:41Z"}]},{"name":"Advertisement","entity_id":"510feb5ac44ecc0002000013","confidence":"low","asset_id":"514a25af0f7ca625870000bd","bounds":{"width":"0.7342105263157894","height":"0.08195292066259808","x":"0.09342105263157894","y":"0.7349607672188317"},"data":{"company":{"value":"Hudson Trust Company","confidence":"low"},"address":{"value":"39th St. at Broadway","confidence":"low"},"goods":{"value":"bank","confidence":"low"}},"revisions":[{"id":"525ffc10ad1f4c0002026960","user":{"name":"User.525ff191ad1f4c0002000225","id":"525ff191ad1f4c0002000225"},"asset_id":"514a25af0f7ca625870000bd","bounds":{"width":"0.7342105263157894","height":"0.08195292066259808","x":"0.09342105263157894","y":"0.7349607672188317"},"data":{"company":"Hudson Trust Company","address":"39th St. at Broadway","goods":"bank"},"entity_id":"510feb5ac44ecc0002000013","created_at":"2013-10-17T15:02:40Z"}]},{"name":"Advertisement","entity_id":"510feb5ac44ecc0002000013","confidence":"low","asset_id":"514a25ba0f7ca625870000c1","bounds":{"width":"0.7039473684210526","height":"0.0658578856152513","x":"0.08421052631578947","y":"0.39428076256499134"},"data":{"company":{"value":"Hotel Traymore","confidence":"low"},"address":{"value":"308-310 West 58th Street, near Col. Circle","confidence":"low"},"goods":{"value":"hotel","confidence":"low"}},"revisions":[{"id":"525ffc11ad1f4c000202697e","user":{"name":"User.525ff191ad1f4c0002000225","id":"525ff191ad1f4c0002000225"},"asset_id":"514a25ba0f7ca625870000c1","bounds":{"width":"0.7039473684210526","height":"0.0658578856152513","x":"0.08421052631578947","y":"0.39428076256499134"},"data":{"company":"Hotel Traymore","address":"308-310 West 58th Street, near Col. Circle","goods":"hotel"},"entity_id":"510feb5ac44ecc0002000013","created_at":"2013-10-17T15:02:41Z"}]},{"name":"Advertisement","entity_id":"510feb5ac44ecc0002000013","confidence":"low","asset_id":"514a25b10f7ca625870000be","bounds":{"width":"0.3460526315789474","height":"0.14904679376083188","x":"0.15263157894736842","y":"0.4324090121317158"},"data":{"company":{"value":"The Columbia Storage Ware-Houses","confidence":"low"},"address":{"value":"","confidence":"low"},"goods":{"value":"storage","confidence":"low"}},"revisions":[{"id":"525ffc10ad1f4c0002026966","user":{"name":"User.525ff191ad1f4c0002000225","id":"525ff191ad1f4c0002000225"},"asset_id":"514a25b10f7ca625870000be","bounds":{"width":"0.3460526315789474","height":"0.14904679376083188","x":"0.15263157894736842","y":"0.4324090121317158"},"data":{"company":"The Columbia Storage Ware-Houses","address":"","goods":"storage"},"entity_id":"510feb5ac44ecc0002000013","created_at":"2013-10-17T15:02:40Z"}]},{"name":"Advertisement","entity_id":"510feb5ac44ecc0002000013","confidence":"low","asset_id":"514a25ab0f7ca625870000bc","bounds":{"width":"0.5789473684210526","height":"0.11421098517872712","x":"0.23421052631578948","y":"0.13862249346120314"},"data":{"company":{"value":"Shanley's","confidence":"low"},"address":{"value":"Broadway, 43d to 44th Streets","confidence":"low"},"goods":{"value":"cabaret","confidence":"low"}},"revisions":[{"id":"525ffc10ad1f4c0002026958","user":{"name":"User.525ff191ad1f4c0002000225","id":"525ff191ad1f4c0002000225"},"asset_id":"514a25ab0f7ca625870000bc","bounds":{"width":"0.5789473684210526","height":"0.11421098517872712","x":"0.23421052631578948","y":"0.13862249346120314"},"data":{"company":"Shanley's","address":"Broadway, 43d to 44th Streets","goods":"cabaret"},"entity_id":"510feb5ac44ecc0002000013","created_at":"2013-10-17T15:02:40Z"}]},{"name":"Advertisement","entity_id":"510feb5ac44ecc0002000013","confidence":"low","asset_id":"514a25af0f7ca625870000bd","bounds":{"width":"0.6881578947368421","height":"0.14995640802092414","x":"0.11710526315789474","y":"0.07759372275501308"},"data":{"company":{"value":"A. Simonson","confidence":"low"},"address":{"value":"506 Fifth Avenue, Near 42 Street, New York City","confidence":"low"},"goods":{"value":"beauty parlor","confidence":"low"}},"revisions":[{"id":"525ffc10ad1f4c000202695e","user":{"name":"User.525ff191ad1f4c0002000225","id":"525ff191ad1f4c0002000225"},"asset_id":"514a25af0f7ca625870000bd","bounds":{"width":"0.6881578947368421","height":"0.14995640802092414","x":"0.11710526315789474","y":"0.07759372275501308"},"data":{"company":"A. Simonson","address":"506 Fifth Avenue, Near 42 Street, New York City","goods":"beauty parlor"},"entity_id":"510feb5ac44ecc0002000013","created_at":"2013-10-17T15:02:40Z"}]},{"name":"Advertisement","entity_id":"510feb5ac44ecc0002000013","confidence":"low","asset_id":"514a25b10f7ca625870000be","bounds":{"width":"0.36447368421052634","height":"0.0415944540727903","x":"0.1368421052631579","y":"0.5996533795493935"},"data":{"company":{"value":"Garfield Tea","confidence":"low"},"address":{"value":"","confidence":"low"},"goods":{"value":"herbal tea laxative","confidence":"low"}},"revisions":[{"id":"525ffc10ad1f4c000202696a","user":{"name":"User.525ff191ad1f4c0002000225","id":"525ff191ad1f4c0002000225"},"asset_id":"514a25b10f7ca625870000be","bounds":{"width":"0.36447368421052634","height":"0.0415944540727903","x":"0.1368421052631579","y":"0.5996533795493935"},"data":{"company":"Garfield Tea","address":"","goods":"herbal tea laxative"},"entity_id":"510feb5ac44ecc0002000013","created_at":"2013-10-17T15:02:40Z"}]},{"name":"Advertisement","entity_id":"510feb5ac44ecc0002000013","confidence":"low","asset_id":"514a25b10f7ca625870000be","bounds":{"width":"0.6960526315789474","height":"0.11611785095320624","x":"0.17894736842105263","y":"0.09185441941074523"},"data":{"company":{"value":"Murray's","confidence":"low"},"address":{"value":"42d St. near B'way","confidence":"low"},"goods":{"value":"restaurant and dancing","confidence":"low"}},"revisions":[{"id":"525ffc10ad1f4c0002026962","user":{"name":"User.525ff191ad1f4c0002000225","id":"525ff191ad1f4c0002000225"},"asset_id":"514a25b10f7ca625870000be","bounds":{"width":"0.6960526315789474","height":"0.11611785095320624","x":"0.17894736842105263","y":"0.09185441941074523"},"data":{"company":"Murray's","address":"42d St. near B'way","goods":"restaurant and dancing"},"entity_id":"510feb5ac44ecc0002000013","created_at":"2013-10-17T15:02:40Z"}]},{"name":"Advertisement","entity_id":"510feb5ac44ecc0002000013","confidence":"low","asset_id":"514a25a80f7ca625870000bb","bounds":{"width":"0.7263157894736842","height":"0.0686359687228497","x":"0.09342105263157894","y":"0.6681146828844483"},"data":{"company":{"value":"Phillips' Digestible Cocoa","confidence":"low"},"address":{"value":"","confidence":"low"},"goods":{"value":"cocoa","confidence":"low"}},"revisions":[{"id":"525ffc10ad1f4c0002026950","user":{"name":"User.525ff191ad1f4c0002000225","id":"525ff191ad1f4c0002000225"},"asset_id":"514a25a80f7ca625870000bb","bounds":{"width":"0.7263157894736842","height":"0.0686359687228497","x":"0.09342105263157894","y":"0.6681146828844483"},"data":{"company":"Phillips' Digestible Cocoa","address":"","goods":"cocoa"},"entity_id":"510feb5ac44ecc0002000013","created_at":"2013-10-17T15:02:40Z"}]},{"name":"Advertisement","entity_id":"510feb5ac44ecc0002000013","confidence":"low","asset_id":"514a25a80f7ca625870000bb","bounds":{"width":"0.7407894736842105","height":"0.0842745438748914","x":"0.07368421052631578","y":"0.8714161598609904"},"data":{"company":{"value":"St. James Importing Co., N. Y., Importers","confidence":"low"},"address":{"value":"","confidence":"low"},"goods":{"value":"Bootz Apricot Liqueur","confidence":"low"}},"revisions":[{"id":"525ffc10ad1f4c0002026956","user":{"name":"User.525ff191ad1f4c0002000225","id":"525ff191ad1f4c0002000225"},"asset_id":"514a25a80f7ca625870000bb","bounds":{"width":"0.7407894736842105","height":"0.0842745438748914","x":"0.07368421052631578","y":"0.8714161598609904"},"data":{"company":"St. James Importing Co., N. Y., Importers","address":"","goods":"Bootz Apricot Liqueur"},"entity_id":"510feb5ac44ecc0002000013","created_at":"2013-10-17T15:02:40Z"}]},{"name":"Advertisement","entity_id":"510feb5ac44ecc0002000013","confidence":"low","asset_id":"514a25a50f7ca625870000ba","bounds":{"width":"0.36973684210526314","height":"0.13032145960034752","x":"0.4855263157894737","y":"0.09817549956559514"},"data":{"company":{"value":"National Biscuit Company","confidence":"low"},"address":{"value":"","confidence":"low"},"goods":{"value":"Rykon Biscuit","confidence":"low"}},"revisions":[{"id":"525ffc10ad1f4c0002026946","user":{"name":"User.525ff191ad1f4c0002000225","id":"525ff191ad1f4c0002000225"},"asset_id":"514a25a50f7ca625870000ba","bounds":{"width":"0.36973684210526314","height":"0.13032145960034752","x":"0.4855263157894737","y":"0.09817549956559514"},"data":{"company":"National Biscuit Company","address":"","goods":"Rykon Biscuit"},"entity_id":"510feb5ac44ecc0002000013","created_at":"2013-10-17T15:02:40Z"}]},{"name":"Advertisement","entity_id":"510feb5ac44ecc0002000013","confidence":"low","asset_id":"514a25a80f7ca625870000bb","bounds":{"width":"0.5605263157894736","height":"0.08774978279756733","x":"0.10789473684210526","y":"0.2701998262380539"},"data":{"company":{"value":"Hofbr\u00e4u Haus","confidence":"low"},"address":{"value":"Broadway & 30th St.","confidence":"low"},"goods":{"value":"restaurant","confidence":"low"}},"revisions":[{"id":"525ffc10ad1f4c000202694e","user":{"name":"User.525ff191ad1f4c0002000225","id":"525ff191ad1f4c0002000225"},"asset_id":"514a25a80f7ca625870000bb","bounds":{"width":"0.5605263157894736","height":"0.08774978279756733","x":"0.10789473684210526","y":"0.2701998262380539"},"data":{"company":"Hofbr\u00e4u Haus","address":"Broadway & 30th St.","goods":"restaurant"},"entity_id":"510feb5ac44ecc0002000013","created_at":"2013-10-17T15:02:40Z"}]},{"name":"Advertisement","entity_id":"510feb5ac44ecc0002000013","confidence":"low","asset_id":"514a25a80f7ca625870000bb","bounds":{"width":"0.7210526315789474","height":"0.05386620330147698","x":"0.1118421052631579","y":"0.21112076455256298"},"data":{"company":{"value":"Sohmer & Co.","confidence":"low"},"address":{"value":"315 Fifth Ave., cor. 32d St.","confidence":"low"},"goods":{"value":"pianos","confidence":"low"}},"revisions":[{"id":"525ffc10ad1f4c000202694c","user":{"name":"User.525ff191ad1f4c0002000225","id":"525ff191ad1f4c0002000225"},"asset_id":"514a25a80f7ca625870000bb","bounds":{"width":"0.7210526315789474","height":"0.05386620330147698","x":"0.1118421052631579","y":"0.21112076455256298"},"data":{"company":"Sohmer & Co.","address":"315 Fifth Ave., cor. 32d St.","goods":"pianos"},"entity_id":"510feb5ac44ecc0002000013","created_at":"2013-10-17T15:02:40Z"}]},{"name":"Advertisement","entity_id":"510feb5ac44ecc0002000013","confidence":"low","asset_id":"514a25a80f7ca625870000bb","bounds":{"width":"0.7460526315789474","height":"0.06429192006950478","x":"0.07368421052631578","y":"0.8201563857515204"},"data":{"company":{"value":"Universal Taximeter Cab Co.","confidence":"low"},"address":{"value":"153 East 53d St.","confidence":"low"},"goods":{"value":"Packard cars for hire","confidence":"low"}},"revisions":[{"id":"525ffc10ad1f4c0002026954","user":{"name":"User.525ff191ad1f4c0002000225","id":"525ff191ad1f4c0002000225"},"asset_id":"514a25a80f7ca625870000bb","bounds":{"width":"0.7460526315789474","height":"0.06429192006950478","x":"0.07368421052631578","y":"0.8201563857515204"},"data":{"company":"Universal Taximeter Cab Co.","address":"153 East 53d St.","goods":"Packard cars for hire"},"entity_id":"510feb5ac44ecc0002000013","created_at":"2013-10-17T15:02:40Z"}]},{"name":"Advertisement","entity_id":"510feb5ac44ecc0002000013","confidence":"low","asset_id":"514a25b40f7ca625870000bf","bounds":{"width":"0.7276315789473684","height":"0.036395147313691506","x":"0.0881578947368421","y":"0.8830155979202773"},"data":{"company":{"value":"Horlick's","confidence":"low"},"address":{"value":"","confidence":"low"},"goods":{"value":"malted milk","confidence":"low"}},"revisions":[{"id":"525ffc11ad1f4c0002026978","user":{"name":"User.525ff191ad1f4c0002000225","id":"525ff191ad1f4c0002000225"},"asset_id":"514a25b40f7ca625870000bf","bounds":{"width":"0.7276315789473684","height":"0.036395147313691506","x":"0.0881578947368421","y":"0.8830155979202773"},"data":{"company":"Horlick's","address":"","goods":"malted milk"},"entity_id":"510feb5ac44ecc0002000013","created_at":"2013-10-17T15:02:41Z"}]},{"name":"Advertisement","entity_id":"510feb5ac44ecc0002000013","confidence":"low","asset_id":"514a25b10f7ca625870000be","bounds":{"width":"0.7736842105263157","height":"0.09878682842287695","x":"0.12894736842105264","y":"0.7175043327556326"},"data":{"company":{"value":"Lovera Cigars","confidence":"low"},"address":{"value":"","confidence":"low"},"goods":{"value":"cigars","confidence":"low"}},"revisions":[{"id":"525ffc11ad1f4c000202696e","user":{"name":"User.525ff191ad1f4c0002000225","id":"525ff191ad1f4c0002000225"},"asset_id":"514a25b10f7ca625870000be","bounds":{"width":"0.7736842105263157","height":"0.09878682842287695","x":"0.12894736842105264","y":"0.7175043327556326"},"data":{"company":"Lovera Cigars","address":"","goods":"cigars"},"entity_id":"510feb5ac44ecc0002000013","created_at":"2013-10-17T15:02:41Z"}]},{"name":"Advertisement","entity_id":"510feb5ac44ecc0002000013","confidence":"low","asset_id":"514a25a80f7ca625870000bb","bounds":{"width":"0.718421052631579","height":"0.03909643788010426","x":"0.09868421052631579","y":"0.7506516072980017"},"data":{"company":{"value":"Horlick's","confidence":"low"},"address":{"value":"","confidence":"low"},"goods":{"value":"malted milk","confidence":"low"}},"revisions":[{"id":"525ffc10ad1f4c0002026952","user":{"name":"User.525ff191ad1f4c0002000225","id":"525ff191ad1f4c0002000225"},"asset_id":"514a25a80f7ca625870000bb","bounds":{"width":"0.718421052631579","height":"0.03909643788010426","x":"0.09868421052631579","y":"0.7506516072980017"},"data":{"company":"Horlick's","address":"","goods":"malted milk"},"entity_id":"510feb5ac44ecc0002000013","created_at":"2013-10-17T15:02:40Z"}]},{"name":"Advertisement","entity_id":"510feb5ac44ecc0002000013","confidence":"low","asset_id":"514a25b10f7ca625870000be","bounds":{"width":"0.35657894736842105","height":"0.20623916811091855","x":"0.531578947368421","y":"0.4289428076256499"},"data":{"company":{"value":"Bryant Park Art and Stationery Shop","confidence":"low"},"address":{"value":"55 West 42d St., New York","confidence":"low"},"goods":{"value":"stationery, books, picture framing, engraving, greeting cards","confidence":"low"}},"revisions":[{"id":"525ffc10ad1f4c0002026968","user":{"name":"User.525ff191ad1f4c0002000225","id":"525ff191ad1f4c0002000225"},"asset_id":"514a25b10f7ca625870000be","bounds":{"width":"0.35657894736842105","height":"0.20623916811091855","x":"0.531578947368421","y":"0.4289428076256499"},"data":{"company":"Bryant Park Art and Stationery Shop","address":"55 West 42d St., New York","goods":"stationery, books, picture framing, engraving, greeting cards"},"entity_id":"510feb5ac44ecc0002000013","created_at":"2013-10-17T15:02:40Z"}]},{"name":"Advertisement","entity_id":"510feb5ac44ecc0002000013","confidence":"low","asset_id":"514a25b40f7ca625870000bf","bounds":{"width":"0.7513157894736842","height":"0.0658578856152513","x":"0.06184210526315789","y":"0.33362218370883883"},"data":{"company":{"value":"Velogen","confidence":"low"},"address":{"value":"","confidence":"low"},"goods":{"value":"skin cream","confidence":"low"}},"revisions":[{"id":"525ffc11ad1f4c0002026972","user":{"name":"User.525ff191ad1f4c0002000225","id":"525ff191ad1f4c0002000225"},"asset_id":"514a25b40f7ca625870000bf","bounds":{"width":"0.7513157894736842","height":"0.0658578856152513","x":"0.06184210526315789","y":"0.33362218370883883"},"data":{"company":"Velogen","address":"","goods":"skin cream"},"entity_id":"510feb5ac44ecc0002000013","created_at":"2013-10-17T15:02:41Z"}]},{"name":"Advertisement","entity_id":"510feb5ac44ecc0002000013","confidence":"low","asset_id":"514a25ab0f7ca625870000bc","bounds":{"width":"0.6355263157894737","height":"0.07933740191804708","x":"0.21447368421052632","y":"0.36617262423714036"},"data":{"company":{"value":"Frank V. Strauss & Co.","confidence":"low"},"address":{"value":"108, 110, 112, 114 Wooster Street, New York","confidence":"low"},"goods":{"value":"programme advertising and publishing house","confidence":"low"}},"revisions":[{"id":"525ffc10ad1f4c000202695a","user":{"name":"User.525ff191ad1f4c0002000225","id":"525ff191ad1f4c0002000225"},"asset_id":"514a25ab0f7ca625870000bc","bounds":{"width":"0.6355263157894737","height":"0.07933740191804708","x":"0.21447368421052632","y":"0.36617262423714036"},"data":{"company":"Frank V. Strauss & Co.","address":"108, 110, 112, 114 Wooster Street, New York","goods":"programme advertising and publishing house"},"entity_id":"510feb5ac44ecc0002000013","created_at":"2013-10-17T15:02:40Z"}]},{"name":"Advertisement","entity_id":"510feb5ac44ecc0002000013","confidence":"low","asset_id":"514a25b70f7ca625870000c0","bounds":{"width":"0.29736842105263156","height":"0.11438474870017331","x":"0.35789473684210526","y":"0.1291161178509532"},"data":{"company":{"value":"Cammeyer","confidence":"low"},"address":{"value":"","confidence":"low"},"goods":{"value":"shoes","confidence":"low"}},"revisions":[{"id":"525ffc11ad1f4c000202697a","user":{"name":"User.525ff191ad1f4c0002000225","id":"525ff191ad1f4c0002000225"},"asset_id":"514a25b70f7ca625870000c0","bounds":{"width":"0.29736842105263156","height":"0.11438474870017331","x":"0.35789473684210526","y":"0.1291161178509532"},"data":{"company":"Cammeyer","address":"","goods":"shoes"},"entity_id":"510feb5ac44ecc0002000013","created_at":"2013-10-17T15:02:41Z"}]},{"name":"Advertisement","entity_id":"510feb5ac44ecc0002000013","confidence":"low","asset_id":"514a25a50f7ca625870000ba","bounds":{"width":"0.4473684210526316","height":"0.09296264118158123","x":"0.4697368421052632","y":"0.8644656820156386"},"data":{"company":{"value":"Rogers Peet Company","confidence":"low"},"address":{"value":"Broadway at Warren St., at 13th St., at 34th St., New York","confidence":"low"},"goods":{"value":"men's and boys' clothing","confidence":"low"}},"revisions":[{"id":"525ffc10ad1f4c000202694a","user":{"name":"User.525ff191ad1f4c0002000225","id":"525ff191ad1f4c0002000225"},"asset_id":"514a25a50f7ca625870000ba","bounds":{"width":"0.4473684210526316","height":"0.09296264118158123","x":"0.4697368421052632","y":"0.8644656820156386"},"data":{"company":"Rogers Peet Company","address":"Broadway at Warren St., at 13th St., at 34th St., New York","goods":"men's and boys' clothing"},"entity_id":"510feb5ac44ecc0002000013","created_at":"2013-10-17T15:02:40Z"}]},{"name":"Advertisement","entity_id":"510feb5ac44ecc0002000013","confidence":"low","asset_id":"514a25c00f7ca625870000c3","bounds":{"width":"0.65","height":"0.014010507880910683","x":"0.1355263157894737","y":"0.5"},"data":{"company":{"value":"Silox Pure Water Co.","confidence":"low"},"address":{"value":"","confidence":"low"},"goods":{"value":"purified water","confidence":"low"}},"revisions":[{"id":"525ffc11ad1f4c0002026994","user":{"name":"User.525ff191ad1f4c0002000225","id":"525ff191ad1f4c0002000225"},"asset_id":"514a25c00f7ca625870000c3","bounds":{"width":"0.65","height":"0.014010507880910683","x":"0.1355263157894737","y":"0.5"},"data":{"company":"Silox Pure Water Co.","address":"","goods":"purified water"},"entity_id":"510feb5ac44ecc0002000013","created_at":"2013-10-17T15:02:41Z"}]},{"name":"Advertisement","entity_id":"510feb5ac44ecc0002000013","confidence":"low","asset_id":"514a25a30f7ca625870000b9","bounds":{"width":"0.6171052631578947","height":"0.1406113537117904","x":"0.10921052631578948","y":"0.8"},"data":{"company":{"value":"12th Night","confidence":"low"},"address":{"value":"","confidence":"low"},"goods":{"value":"cigarettes","confidence":"low"}},"revisions":[{"id":"525ffc10ad1f4c0002026944","user":{"name":"User.525ff191ad1f4c0002000225","id":"525ff191ad1f4c0002000225"},"asset_id":"514a25a30f7ca625870000b9","bounds":{"width":"0.6171052631578947","height":"0.1406113537117904","x":"0.10921052631578948","y":"0.8"},"data":{"company":"12th Night","address":"","goods":"cigarettes"},"entity_id":"510feb5ac44ecc0002000013","created_at":"2013-10-17T15:02:40Z"}]},{"name":"Advertisement","entity_id":"510feb5ac44ecc0002000013","confidence":"low","asset_id":"514a25b10f7ca625870000be","bounds":{"width":"0.7368421052631578","height":"0.11005199306759099","x":"0.14868421052631578","y":"0.31022530329289427"},"data":{"company":{"value":"Antikamnia Tablets","confidence":"low"},"address":{"value":"","confidence":"low"},"goods":{"value":"tablets for headaches, neuralgias, colds, womens aches & ills","confidence":"low"}},"revisions":[{"id":"525ffc10ad1f4c0002026964","user":{"name":"User.525ff191ad1f4c0002000225","id":"525ff191ad1f4c0002000225"},"asset_id":"514a25b10f7ca625870000be","bounds":{"width":"0.7368421052631578","height":"0.11005199306759099","x":"0.14868421052631578","y":"0.31022530329289427"},"data":{"company":"Antikamnia Tablets","address":"","goods":"tablets for headaches, neuralgias, colds, womens aches & ills"},"entity_id":"510feb5ac44ecc0002000013","created_at":"2013-10-17T15:02:40Z"}]},{"name":"Advertisement","entity_id":"510feb5ac44ecc0002000013","confidence":"low","asset_id":"514a25a50f7ca625870000ba","bounds":{"width":"0.37894736842105264","height":"0.10512597741094701","x":"0.5092105263157894","y":"0.5195482189400521"},"data":{"company":{"value":"Clysmic","confidence":"low"},"address":{"value":"","confidence":"low"},"goods":{"value":"table waters","confidence":"low"}},"revisions":[{"id":"525ffc10ad1f4c0002026948","user":{"name":"User.525ff191ad1f4c0002000225","id":"525ff191ad1f4c0002000225"},"asset_id":"514a25a50f7ca625870000ba","bounds":{"width":"0.37894736842105264","height":"0.10512597741094701","x":"0.5092105263157894","y":"0.5195482189400521"},"data":{"company":"Clysmic","address":"","goods":"table waters"},"entity_id":"510feb5ac44ecc0002000013","created_at":"2013-10-17T15:02:40Z"}]},{"name":"Advertisement","entity_id":"510feb5ac44ecc0002000013","confidence":"low","asset_id":"514a25ab0f7ca625870000bc","bounds":{"width":"0.7315789473684211","height":"0.05841325196163906","x":"0.14605263157894738","y":"0.8761987794245859"},"data":{"company":{"value":"Peter Doelger First Prize Brewery","confidence":"low"},"address":{"value":"407-455 East 55th Street, New York City","confidence":"low"},"goods":{"value":"beer","confidence":"low"}},"revisions":[{"id":"525ffc10ad1f4c000202695c","user":{"name":"User.525ff191ad1f4c0002000225","id":"525ff191ad1f4c0002000225"},"asset_id":"514a25ab0f7ca625870000bc","bounds":{"width":"0.7315789473684211","height":"0.05841325196163906","x":"0.14605263157894738","y":"0.8761987794245859"},"data":{"company":"Peter Doelger First Prize Brewery","address":"407-455 East 55th Street, New York City","goods":"beer"},"entity_id":"510feb5ac44ecc0002000013","created_at":"2013-10-17T15:02:40Z"}]},{"name":"Advertisement","entity_id":"510feb5ac44ecc0002000013","confidence":"low","asset_id":"514a25c00f7ca625870000c3","bounds":{"width":"0.47368421052631576","height":"0.03064798598949212","x":"0.21973684210526315","y":"0.3213660245183888"},"data":{"company":{"value":"Dodge & Castle","confidence":"low"},"address":{"value":"New York    ","confidence":"low"},"goods":{"value":"scenery painters","confidence":"low"}},"revisions":[{"id":"525ffc11ad1f4c0002026988","user":{"name":"User.525ff191ad1f4c0002000225","id":"525ff191ad1f4c0002000225"},"asset_id":"514a25c00f7ca625870000c3","bounds":{"width":"0.47368421052631576","height":"0.03064798598949212","x":"0.21973684210526315","y":"0.3213660245183888"},"data":{"company":"Dodge & Castle","address":"New York    ","goods":"scenery painters"},"entity_id":"510feb5ac44ecc0002000013","created_at":"2013-10-17T15:02:41Z"}]},{"name":"Advertisement","entity_id":"510feb5ac44ecc0002000013","confidence":"low","asset_id":"514a25b40f7ca625870000bf","bounds":{"width":"0.6697368421052632","height":"0.14038128249566725","x":"0.11447368421052631","y":"0.15771230502599653"},"data":{"company":{"value":"Bustanoby's Restaurant","confidence":"low"},"address":{"value":"39th Street, West, opp. Maxine Elliott's Theatre","confidence":"low"},"goods":{"value":"restaurant and dancing","confidence":"low"}},"revisions":[{"id":"525ffc11ad1f4c0002026970","user":{"name":"User.525ff191ad1f4c0002000225","id":"525ff191ad1f4c0002000225"},"asset_id":"514a25b40f7ca625870000bf","bounds":{"width":"0.6697368421052632","height":"0.14038128249566725","x":"0.11447368421052631","y":"0.15771230502599653"},"data":{"company":"Bustanoby's Restaurant","address":"39th Street, West, opp. Maxine Elliott's Theatre","goods":"restaurant and dancing"},"entity_id":"510feb5ac44ecc0002000013","created_at":"2013-10-17T15:02:41Z"}]},{"name":"Advertisement","entity_id":"510feb5ac44ecc0002000013","confidence":"low","asset_id":"514a25b40f7ca625870000bf","bounds":{"width":"0.7421052631578947","height":"0.08232235701906412","x":"0.06973684210526315","y":"0.4098786828422877"},"data":{"company":{"value":"St. James Importing Co., N. Y., Importers","confidence":"low"},"address":{"value":"","confidence":"low"},"goods":{"value":"Whitbread English Ale and Stout","confidence":"low"}},"revisions":[{"id":"525ffc11ad1f4c0002026974","user":{"name":"User.525ff191ad1f4c0002000225","id":"525ff191ad1f4c0002000225"},"asset_id":"514a25b40f7ca625870000bf","bounds":{"width":"0.7421052631578947","height":"0.08232235701906412","x":"0.06973684210526315","y":"0.4098786828422877"},"data":{"company":"St. James Importing Co., N. Y., Importers","address":"","goods":"Whitbread English Ale and Stout"},"entity_id":"510feb5ac44ecc0002000013","created_at":"2013-10-17T15:02:41Z"}]},{"name":"Advertisement","entity_id":"510feb5ac44ecc0002000013","confidence":"low","asset_id":"514a25b40f7ca625870000bf","bounds":{"width":"0.7236842105263158","height":"0.1386481802426343","x":"0.0868421052631579","y":"0.733102253032929"},"data":{"company":{"value":"Lucile Ltd.","confidence":"low"},"address":{"value":"17 West 36th Street, New York","confidence":"low"},"goods":{"value":"gowns, wraps, millinery, lingerie, corsets","confidence":"low"}},"revisions":[{"id":"525ffc11ad1f4c0002026976","user":{"name":"User.525ff191ad1f4c0002000225","id":"525ff191ad1f4c0002000225"},"asset_id":"514a25b40f7ca625870000bf","bounds":{"width":"0.7236842105263158","height":"0.1386481802426343","x":"0.0868421052631579","y":"0.733102253032929"},"data":{"company":"Lucile Ltd.","address":"17 West 36th Street, New York","goods":"gowns, wraps, millinery, lingerie, corsets"},"entity_id":"510feb5ac44ecc0002000013","created_at":"2013-10-17T15:02:41Z"}]},{"name":"Advertisement","entity_id":"510feb5ac44ecc0002000013","confidence":"low","asset_id":"514a25ba0f7ca625870000c1","bounds":{"width":"0.7263157894736842","height":"0.12998266897746968","x":"0.07763157894736842","y":"0.1265164644714038"},"data":{"company":{"value":"La Parisienne Rotisserie","confidence":"low"},"address":{"value":"630 8th Ave., bet. 40th and 41st Streets","confidence":"low"},"goods":{"value":"restaurant","confidence":"low"}},"revisions":[{"id":"525ffc11ad1f4c000202697c","user":{"name":"User.525ff191ad1f4c0002000225","id":"525ff191ad1f4c0002000225"},"asset_id":"514a25ba0f7ca625870000c1","bounds":{"width":"0.7263157894736842","height":"0.12998266897746968","x":"0.07763157894736842","y":"0.1265164644714038"},"data":{"company":"La Parisienne Rotisserie","address":"630 8th Ave., bet. 40th and 41st Streets","goods":"restaurant"},"entity_id":"510feb5ac44ecc0002000013","created_at":"2013-10-17T15:02:41Z"}]},{"name":"Advertisement","entity_id":"510feb5ac44ecc0002000013","confidence":"low","asset_id":"514a25ba0f7ca625870000c1","bounds":{"width":"0.756578947368421","height":"0.07365684575389948","x":"0.07236842105263158","y":"0.7712305025996534"},"data":{"company":{"value":"Physical Culture Restaurants","confidence":"low"},"address":{"value":"","confidence":"low"},"goods":{"value":"\"Caterers of Nature's Pure Foods\"","confidence":"low"}},"revisions":[{"id":"525ffc11ad1f4c0002026980","user":{"name":"User.525ff191ad1f4c0002000225","id":"525ff191ad1f4c0002000225"},"asset_id":"514a25ba0f7ca625870000c1","bounds":{"width":"0.756578947368421","height":"0.07365684575389948","x":"0.07236842105263158","y":"0.7712305025996534"},"data":{"company":"Physical Culture Restaurants","address":"","goods":"\"Caterers of Nature's Pure Foods\""},"entity_id":"510feb5ac44ecc0002000013","created_at":"2013-10-17T15:02:41Z"}]},{"name":"Advertisement","entity_id":"510feb5ac44ecc0002000013","confidence":"low","asset_id":"514a25c00f7ca625870000c3","bounds":{"width":"0.7236842105263158","height":"0.16024518388791595","x":"0.10657894736842105","y":"0.08844133099824869"},"data":{"company":{"value":"Keeley Cure","confidence":"low"},"address":{"value":"Keeley Institute, White Plains, N. Y.","confidence":"low"},"goods":{"value":"remedy for alcoholoism, drug using, and nerve exhaustion","confidence":"low"}},"revisions":[{"id":"525ffc11ad1f4c0002026986","user":{"name":"User.525ff191ad1f4c0002000225","id":"525ff191ad1f4c0002000225"},"asset_id":"514a25c00f7ca625870000c3","bounds":{"width":"0.7236842105263158","height":"0.16024518388791595","x":"0.10657894736842105","y":"0.08844133099824869"},"data":{"company":"Keeley Cure","address":"Keeley Institute, White Plains, N. Y.","goods":"remedy for alcoholoism, drug using, and nerve exhaustion"},"entity_id":"510feb5ac44ecc0002000013","created_at":"2013-10-17T15:02:41Z"}]},{"name":"Advertisement","entity_id":"510feb5ac44ecc0002000013","confidence":"low","asset_id":"514a25c00f7ca625870000c3","bounds":{"width":"0.7460526315789474","height":"0.07618213660245183","x":"0.0868421052631579","y":"0.5280210157618214"},"data":{"company":{"value":"The Broadway Art Stores","confidence":"low"},"address":{"value":"","confidence":"low"},"goods":{"value":"sheet music, post cards, souvenirs of New York","confidence":"low"}},"revisions":[{"id":"525ffc11ad1f4c0002026996","user":{"name":"User.525ff191ad1f4c0002000225","id":"525ff191ad1f4c0002000225"},"asset_id":"514a25c00f7ca625870000c3","bounds":{"width":"0.7460526315789474","height":"0.07618213660245183","x":"0.0868421052631579","y":"0.5280210157618214"},"data":{"company":"The Broadway Art Stores","address":"","goods":"sheet music, post cards, souvenirs of New York"},"entity_id":"510feb5ac44ecc0002000013","created_at":"2013-10-17T15:02:41Z"}]},{"name":"Advertisement","entity_id":"510feb5ac44ecc0002000013","confidence":"low","asset_id":"514a25c00f7ca625870000c3","bounds":{"width":"0.7236842105263158","height":"0.05691768826619965","x":"0.0881578947368421","y":"0.87215411558669"},"data":{"company":{"value":"Stein Tire & Rubber Company","confidence":"low"},"address":{"value":"Stein Building, 1741 Broadway, New York City","confidence":"low"},"goods":{"value":"automobile tires","confidence":"low"}},"revisions":[{"id":"525ffc11ad1f4c0002026998","user":{"name":"User.525ff191ad1f4c0002000225","id":"525ff191ad1f4c0002000225"},"asset_id":"514a25c00f7ca625870000c3","bounds":{"width":"0.7236842105263158","height":"0.05691768826619965","x":"0.0881578947368421","y":"0.87215411558669"},"data":{"company":"Stein Tire & Rubber Company","address":"Stein Building, 1741 Broadway, New York City","goods":"automobile tires"},"entity_id":"510feb5ac44ecc0002000013","created_at":"2013-10-17T15:02:41Z"}]}]}}