{"uri":"http://labs.nypl.org/playbills-10-00261","template_id":"510feb5ac44ecc0002000001","assets":[{"id":"514a21e00f7ca62513000110","width":1000,"height":1532,"uri":"https://s3.amazonaws.com/programs-cropped.nypl.org/10/00261.jpg","thumb_uri":"https://s3.amazonaws.com/programs-cropped.nypl.org/thumbs/10/00261.jpg"},{"id":"514a21e00f7ca62513000111","width":1000,"height":1550,"uri":"https://s3.amazonaws.com/programs-cropped.nypl.org/10/00262.1.jpg","thumb_uri":"https://s3.amazonaws.com/programs-cropped.nypl.org/thumbs/10/00262.1.jpg"},{"id":"514a21e10f7ca62513000112","width":1000,"height":1550,"uri":"https://s3.amazonaws.com/programs-cropped.nypl.org/10/00262.2.jpg","thumb_uri":"https://s3.amazonaws.com/programs-cropped.nypl.org/thumbs/10/00262.2.jpg"},{"id":"514a21e30f7ca62513000113","width":1000,"height":1506,"uri":"https://s3.amazonaws.com/programs-cropped.nypl.org/10/00263.jpg","thumb_uri":"https://s3.amazonaws.com/programs-cropped.nypl.org/thumbs/10/00263.jpg"}],"transcription":{"annotations":[{"name":"Advertisement","entity_id":"510feb5ac44ecc0002000013","confidence":"low","asset_id":"514a21e00f7ca62513000110","bounds":{"width":"0.738","height":"0.19245920090039392","x":"0.047","y":"0.7191896454698931"},"data":{"company":{"value":"Little Cigars","confidence":"low"},"address":{"value":"","confidence":"low"},"goods":{"value":"cigars","confidence":"low"}},"revisions":[{"id":"51511a8d74cbf600020014d8","user":{"name":"User.514a3a0a94f50b0002000f1f","id":"514a3a0a94f50b0002000f1f"},"asset_id":"514a21e00f7ca62513000110","bounds":{"width":"0.738","height":"0.19245920090039392","x":"0.047","y":"0.7191896454698931"},"data":{"company":"Little Cigars","address":"","goods":"cigars"},"entity_id":"510feb5ac44ecc0002000013","created_at":"2013-03-26T03:48:29Z"}]},{"name":"Advertisement","entity_id":"510feb5ac44ecc0002000013","confidence":"low","asset_id":"514a21e00f7ca62513000111","bounds":{"width":"0.35526315789473683","height":"0.029711375212224108","x":"0.24605263157894736","y":"0.7436332767402377"},"data":{"company":{"value":"Garfield Tea","confidence":"low"},"address":{"value":"","confidence":"low"},"goods":{"value":"herbal tea laxative and headache powders","confidence":"low"}},"revisions":[{"id":"5158a0f3bf70110002002903","user":{"name":"User.51583e25438cc10002000112","id":"51583e25438cc10002000112"},"asset_id":"514a21e00f7ca62513000111","bounds":{"width":"0.35526315789473683","height":"0.029711375212224108","x":"0.24605263157894736","y":"0.7436332767402377"},"data":{"company":"Garfield Tea","address":"","goods":"herbal tea laxative and headache powders"},"entity_id":"510feb5ac44ecc0002000013","created_at":"2013-03-31T20:47:47Z"}]},{"name":"Advertisement","entity_id":"510feb5ac44ecc0002000013","confidence":"low","asset_id":"514a21e10f7ca62513000112","bounds":{"width":"0.7868421052631579","height":"0.08488964346349745","x":"0.035526315789473684","y":"0.8166383701188455"},"data":{"company":{"value":"Hughes","confidence":"low"},"address":{"value":"29 Flatbush Av. 68-70 Court St.","confidence":"low"},"goods":{"value":"optometry","confidence":"low"}},"revisions":[{"id":"5158a0f3bf70110002002911","user":{"name":"User.51583e25438cc10002000112","id":"51583e25438cc10002000112"},"asset_id":"514a21e10f7ca62513000112","bounds":{"width":"0.7868421052631579","height":"0.08488964346349745","x":"0.035526315789473684","y":"0.8166383701188455"},"data":{"company":"Hughes","address":"29 Flatbush Av. 68-70 Court St.","goods":"optometry"},"entity_id":"510feb5ac44ecc0002000013","created_at":"2013-03-31T20:47:47Z"}]},{"name":"Advertisement","entity_id":"510feb5ac44ecc0002000013","confidence":"low","asset_id":"514a21e10f7ca62513000112","bounds":{"width":"0.7578947368421053","height":"0.05602716468590832","x":"0.017105263157894738","y":"0.6876061120543294"},"data":{"company":{"value":"Horton's Ice Cream","confidence":"low"},"address":{"value":"","confidence":"low"},"goods":{"value":"ice cream","confidence":"low"}},"revisions":[{"id":"5158a0f3bf7011000200290f","user":{"name":"User.51583e25438cc10002000112","id":"51583e25438cc10002000112"},"asset_id":"514a21e10f7ca62513000112","bounds":{"width":"0.7578947368421053","height":"0.05602716468590832","x":"0.017105263157894738","y":"0.6876061120543294"},"data":{"company":"Horton's Ice Cream","address":"","goods":"ice cream"},"entity_id":"510feb5ac44ecc0002000013","created_at":"2013-03-31T20:47:47Z"}]},{"name":"Advertisement","entity_id":"510feb5ac44ecc0002000013","confidence":"low","asset_id":"514a21e00f7ca62513000110","bounds":{"width":"0.7907894736842105","height":"0.08848797250859107","x":"0.04736842105263158","y":"0.7620274914089347"},"data":{"company":{"value":"Between the Acts Little Cigars","confidence":"low"},"address":{"value":"","confidence":"low"},"goods":{"value":"cigars","confidence":"low"}},"revisions":[{"id":"5158a0f3bf701100020028fb","user":{"name":"User.51583e25438cc10002000112","id":"51583e25438cc10002000112"},"asset_id":"514a21e00f7ca62513000110","bounds":{"width":"0.7907894736842105","height":"0.08848797250859107","x":"0.04736842105263158","y":"0.7620274914089347"},"data":{"company":"Between the Acts Little Cigars","address":"","goods":"cigars"},"entity_id":"510feb5ac44ecc0002000013","created_at":"2013-03-31T20:47:47Z"}]},{"name":"Advertisement","entity_id":"510feb5ac44ecc0002000013","confidence":"low","asset_id":"514a21e10f7ca62513000112","bounds":{"width":"0.3736842105263158","height":"0.007640067911714771","x":"0.23157894736842105","y":"0.49830220713073003"},"data":{"company":{"value":"Hudson Construction Co.","confidence":"low"},"address":{"value":"","confidence":"low"},"goods":{"value":"scenery construction","confidence":"low"}},"revisions":[{"id":"5158a0f3bf70110002002909","user":{"name":"User.51583e25438cc10002000112","id":"51583e25438cc10002000112"},"asset_id":"514a21e10f7ca62513000112","bounds":{"width":"0.3736842105263158","height":"0.007640067911714771","x":"0.23157894736842105","y":"0.49830220713073003"},"data":{"company":"Hudson Construction Co.","address":"","goods":"scenery construction"},"entity_id":"510feb5ac44ecc0002000013","created_at":"2013-03-31T20:47:47Z"}]},{"name":"Advertisement","entity_id":"510feb5ac44ecc0002000013","confidence":"low","asset_id":"514a21e00f7ca62513000111","bounds":{"width":"0.5855263157894737","height":"0.08149405772495756","x":"0.2381578947368421","y":"0.13921901528013583"},"data":{"company":{"value":"Chiclets","confidence":"low"},"address":{"value":"","confidence":"low"},"goods":{"value":"chewing gum","confidence":"low"}},"revisions":[{"id":"5158a0f3bf701100020028fd","user":{"name":"User.51583e25438cc10002000112","id":"51583e25438cc10002000112"},"asset_id":"514a21e00f7ca62513000111","bounds":{"width":"0.5855263157894737","height":"0.08149405772495756","x":"0.2381578947368421","y":"0.13921901528013583"},"data":{"company":"Chiclets","address":"","goods":"chewing gum"},"entity_id":"510feb5ac44ecc0002000013","created_at":"2013-03-31T20:47:47Z"}]},{"name":"Advertisement","entity_id":"510feb5ac44ecc0002000013","confidence":"low","asset_id":"514a21e00f7ca62513000111","bounds":{"width":"0.375","height":"0.05263157894736842","x":"0.5342105263157895","y":"0.6120543293718166"},"data":{"company":{"value":"Frank V. Strauss & Co.","confidence":"low"},"address":{"value":"108-114 Wooster St.","confidence":"low"},"goods":{"value":"theatre programs","confidence":"low"}},"revisions":[{"id":"5158a0f3bf70110002002901","user":{"name":"User.51583e25438cc10002000112","id":"51583e25438cc10002000112"},"asset_id":"514a21e00f7ca62513000111","bounds":{"width":"0.375","height":"0.05263157894736842","x":"0.5342105263157895","y":"0.6120543293718166"},"data":{"company":"Frank V. Strauss & Co.","address":"108-114 Wooster St.","goods":"theatre programs"},"entity_id":"510feb5ac44ecc0002000013","created_at":"2013-03-31T20:47:47Z"}]},{"name":"Advertisement","entity_id":"510feb5ac44ecc0002000013","confidence":"low","asset_id":"514a21e00f7ca62513000111","bounds":{"width":"0.7631578947368421","height":"0.09422750424448217","x":"0.16842105263157894","y":"0.44821731748726656"},"data":{"company":{"value":"The Jefferson Restaurant","confidence":"low"},"address":{"value":"5 and 7 Jefferson Street, Cor. Broadway and Myrtle Ave.","confidence":"low"},"goods":{"value":"restaurant","confidence":"low"}},"revisions":[{"id":"5158a0f3bf701100020028ff","user":{"name":"User.51583e25438cc10002000112","id":"51583e25438cc10002000112"},"asset_id":"514a21e00f7ca62513000111","bounds":{"width":"0.7631578947368421","height":"0.09422750424448217","x":"0.16842105263157894","y":"0.44821731748726656"},"data":{"company":"The Jefferson Restaurant","address":"5 and 7 Jefferson Street, Cor. Broadway and Myrtle Ave.","goods":"restaurant"},"entity_id":"510feb5ac44ecc0002000013","created_at":"2013-03-31T20:47:47Z"}]},{"name":"Advertisement","entity_id":"510feb5ac44ecc0002000013","confidence":"low","asset_id":"514a21e30f7ca62513000113","bounds":{"width":"0.6802631578947368","height":"0.05240174672489083","x":"0.19078947368421054","y":"0.4183406113537118"},"data":{"company":{"value":"Sohmer & Co.","confidence":"low"},"address":{"value":"315 Fifth Avenue, Cor. 32d St., N.Y.","confidence":"low"},"goods":{"value":"pianos","confidence":"low"}},"revisions":[{"id":"5158a0f3bf70110002002913","user":{"name":"User.51583e25438cc10002000112","id":"51583e25438cc10002000112"},"asset_id":"514a21e30f7ca62513000113","bounds":{"width":"0.6802631578947368","height":"0.05240174672489083","x":"0.19078947368421054","y":"0.4183406113537118"},"data":{"company":"Sohmer & Co.","address":"315 Fifth Avenue, Cor. 32d St., N.Y.","goods":"pianos"},"entity_id":"510feb5ac44ecc0002000013","created_at":"2013-03-31T20:47:47Z"}]},{"name":"Advertisement","entity_id":"510feb5ac44ecc0002000013","confidence":"low","asset_id":"514a21e10f7ca62513000112","bounds":{"width":"0.7052631578947368","height":"0.050933786078098474","x":"0.05263157894736842","y":"0.23089983022071306"},"data":{"company":{"value":"The Sterling Piano Co.","confidence":"low"},"address":{"value":"518-520 Fulton St., Cor. Hanover Pl., Brooklyn, N.Y.","confidence":"low"},"goods":{"value":"pianos","confidence":"low"}},"revisions":[{"id":"5158a0f3bf70110002002905","user":{"name":"User.51583e25438cc10002000112","id":"51583e25438cc10002000112"},"asset_id":"514a21e10f7ca62513000112","bounds":{"width":"0.7052631578947368","height":"0.050933786078098474","x":"0.05263157894736842","y":"0.23089983022071306"},"data":{"company":"The Sterling Piano Co.","address":"518-520 Fulton St., Cor. Hanover Pl., Brooklyn, N.Y.","goods":"pianos"},"entity_id":"510feb5ac44ecc0002000013","created_at":"2013-03-31T20:47:47Z"}]},{"name":"Advertisement","entity_id":"510feb5ac44ecc0002000013","confidence":"low","asset_id":"514a21e30f7ca62513000113","bounds":{"width":"0.3131578947368421","height":"0.07598253275109171","x":"0.3592105263157895","y":"0.7956331877729258"},"data":{"company":{"value":"Alfred H. Smith Company","confidence":"low"},"address":{"value":"39 West 33d Street, New York","confidence":"low"},"goods":{"value":"Kleanwell toothbrushes","confidence":"low"}},"revisions":[{"id":"5158a0f3bf70110002002915","user":{"name":"User.51583e25438cc10002000112","id":"51583e25438cc10002000112"},"asset_id":"514a21e30f7ca62513000113","bounds":{"width":"0.3131578947368421","height":"0.07598253275109171","x":"0.3592105263157895","y":"0.7956331877729258"},"data":{"company":"Alfred H. Smith Company","address":"39 West 33d Street, New York","goods":"Kleanwell toothbrushes"},"entity_id":"510feb5ac44ecc0002000013","created_at":"2013-03-31T20:47:47Z"}]},{"name":"Headliner","entity_id":"513a55c45d5ae90002000013","confidence":"high","asset_id":"514a21e00f7ca62513000110","bounds":{"width":"0.4146825396825397","height":"0.018134715025906734","x":"0.2123015873015873","y":"0.43523316062176165"},"data":{"actor":{"value":"Lewis S. Stone","confidence":"high"}},"revisions":[{"id":"514c7bebd704c2000200c77a","user":{"name":"User.514c78887a2a4e000200d0fe","id":"514c78887a2a4e000200d0fe"},"asset_id":"514a21e00f7ca62513000110","bounds":{"width":"0.4146825396825397","height":"0.018134715025906734","x":"0.2123015873015873","y":"0.43523316062176165"},"data":{"actor":"Lewis S. Stone"},"entity_id":"513a55c45d5ae90002000013","created_at":"2013-03-22T15:42:35Z"},{"id":"51511a8d74cbf600020014d6","user":{"name":"User.514a3a0a94f50b0002000f1f","id":"514a3a0a94f50b0002000f1f"},"asset_id":"514a21e00f7ca62513000110","bounds":{"width":"0.415","height":"0.017445132245357344","x":"0.212","y":"0.4355655599324705"},"data":{"actor":"Lewis S. Stone"},"entity_id":"513a55c45d5ae90002000013","created_at":"2013-03-26T03:48:29Z"},{"id":"5158a0f3bf701100020028d9","user":{"name":"User.51583e25438cc10002000112","id":"51583e25438cc10002000112"},"asset_id":"514a21e00f7ca62513000110","bounds":{"width":"0.41578947368421054","height":"0.01718213058419244","x":"0.2118421052631579","y":"0.43556701030927835"},"data":{"actor":"Lewis S. Stone"},"entity_id":"513a55c45d5ae90002000013","created_at":"2013-03-31T20:47:47Z"}]},{"name":"Cast Member","entity_id":"510feb5ac44ecc000200000c","confidence":"low","asset_id":"514a21e00f7ca62513000110","bounds":{"width":"0.717","height":"0.011254924029262802","x":"0.055","y":"0.6494091164884637"},"data":{"character":{"value":"Amy Foster","confidence":"medium"},"description":{"value":"","confidence":"medium"},"actor":{"value":"Daisy Adams","confidence":"low"}},"revisions":[{"id":"51511a8c74cbf600020014be","user":{"name":"User.514a3a0a94f50b0002000f1f","id":"514a3a0a94f50b0002000f1f"},"asset_id":"514a21e00f7ca62513000110","bounds":{"width":"0.717","height":"0.011254924029262802","x":"0.055","y":"0.6494091164884637"},"data":{"character":"Amy Foster","description":"","actor":"Daisy Adams"},"entity_id":"510feb5ac44ecc000200000c","created_at":"2013-03-26T03:48:28Z"},{"id":"5158a0f3bf701100020028f7","user":{"name":"User.51583e25438cc10002000112","id":"51583e25438cc10002000112"},"asset_id":"514a21e00f7ca62513000110","bounds":{"width":"0.75","height":"0.01718213058419244","x":"0.05526315789473684","y":"0.6434707903780069"},"data":{"character":"Amy Foster","description":"","actor":"Daisy Adamy"},"entity_id":"510feb5ac44ecc000200000c","created_at":"2013-03-31T20:47:47Z"}]},{"name":"Cast Member","entity_id":"510feb5ac44ecc000200000c","confidence":"low","asset_id":"514a21e00f7ca62513000110","bounds":{"width":"0.722","height":"0.011254924029262802","x":"0.056","y":"0.5537422622397299"},"data":{"character":{"value":"Boney","confidence":"medium"},"description":{"value":"","confidence":"medium"},"actor":{"value":"Franke Sylvester","confidence":"low"}},"revisions":[{"id":"51511a8d74cbf600020014ce","user":{"name":"User.514a3a0a94f50b0002000f1f","id":"514a3a0a94f50b0002000f1f"},"asset_id":"514a21e00f7ca62513000110","bounds":{"width":"0.722","height":"0.011254924029262802","x":"0.056","y":"0.5537422622397299"},"data":{"character":"Boney","description":"","actor":"Franke Sylvester"},"entity_id":"510feb5ac44ecc000200000c","created_at":"2013-03-26T03:48:29Z"},{"id":"5158a0f3bf701100020028e7","user":{"name":"User.51583e25438cc10002000112","id":"51583e25438cc10002000112"},"asset_id":"514a21e00f7ca62513000110","bounds":{"width":"0.7381578947368421","height":"0.01718213058419244","x":"0.056578947368421055","y":"0.5463917525773195"},"data":{"character":"Boney","description":"","actor":"Frank Sylvester"},"entity_id":"510feb5ac44ecc000200000c","created_at":"2013-03-31T20:47:47Z"}]},{"name":"Cast Member","entity_id":"510feb5ac44ecc000200000c","confidence":"medium","asset_id":"514a21e00f7ca62513000110","bounds":{"width":"0.721","height":"0.011254924029262802","x":"0.056","y":"0.5171637591446258"},"data":{"character":{"value":"Sidney Parker","confidence":"medium"},"description":{"value":"","confidence":"medium"},"actor":{"value":"Albert Sackett","confidence":"medium"}},"revisions":[{"id":"51511a8d74cbf600020014d4","user":{"name":"User.514a3a0a94f50b0002000f1f","id":"514a3a0a94f50b0002000f1f"},"asset_id":"514a21e00f7ca62513000110","bounds":{"width":"0.721","height":"0.011254924029262802","x":"0.056","y":"0.5171637591446258"},"data":{"character":"Sidney Parker","description":"","actor":"Albert Sackett"},"entity_id":"510feb5ac44ecc000200000c","created_at":"2013-03-26T03:48:29Z"},{"id":"5158a0f3bf701100020028e1","user":{"name":"User.51583e25438cc10002000112","id":"51583e25438cc10002000112"},"asset_id":"514a21e00f7ca62513000110","bounds":{"width":"0.7381578947368421","height":"0.018900343642611682","x":"0.05789473684210526","y":"0.5085910652920962"},"data":{"character":"Sidney Parker","description":"","actor":"Albert Sackett"},"entity_id":"510feb5ac44ecc000200000c","created_at":"2013-03-31T20:47:47Z"}]},{"name":"Cast Member","entity_id":"510feb5ac44ecc000200000c","confidence":"medium","asset_id":"514a21e00f7ca62513000110","bounds":{"width":"0.732","height":"0.011254924029262802","x":"0.045","y":"0.5649971862689926"},"data":{"character":{"value":"Tim McMahon","confidence":"medium"},"description":{"value":"","confidence":"medium"},"actor":{"value":"Albert Sackett","confidence":"medium"}},"revisions":[{"id":"51511a8d74cbf600020014cc","user":{"name":"User.514a3a0a94f50b0002000f1f","id":"514a3a0a94f50b0002000f1f"},"asset_id":"514a21e00f7ca62513000110","bounds":{"width":"0.732","height":"0.011254924029262802","x":"0.045","y":"0.5649971862689926"},"data":{"character":"Tim McMahon","description":"","actor":"Albert Sackett"},"entity_id":"510feb5ac44ecc000200000c","created_at":"2013-03-26T03:48:29Z"},{"id":"5158a0f3bf701100020028e9","user":{"name":"User.51583e25438cc10002000112","id":"51583e25438cc10002000112"},"asset_id":"514a21e00f7ca62513000110","bounds":{"width":"0.743421052631579","height":"0.01718213058419244","x":"0.04473684210526316","y":"0.5575601374570447"},"data":{"character":"Tim McMahon","description":"","actor":"Albert Sackett"},"entity_id":"510feb5ac44ecc000200000c","created_at":"2013-03-31T20:47:47Z"}]},{"name":"Cast Member","entity_id":"510feb5ac44ecc000200000c","confidence":"medium","asset_id":"514a21e00f7ca62513000110","bounds":{"width":"0.721","height":"0.011254924029262802","x":"0.056","y":"0.5773776027011818"},"data":{"character":{"value":"Bill Fagan","confidence":"medium"},"description":{"value":"","confidence":"medium"},"actor":{"value":"Henry Thompson","confidence":"medium"}},"revisions":[{"id":"51511a8d74cbf600020014ca","user":{"name":"User.514a3a0a94f50b0002000f1f","id":"514a3a0a94f50b0002000f1f"},"asset_id":"514a21e00f7ca62513000110","bounds":{"width":"0.721","height":"0.011254924029262802","x":"0.056","y":"0.5773776027011818"},"data":{"character":"Bill Fagan","description":"","actor":"Henry Thompson"},"entity_id":"510feb5ac44ecc000200000c","created_at":"2013-03-26T03:48:29Z"},{"id":"5158a0f3bf701100020028eb","user":{"name":"User.51583e25438cc10002000112","id":"51583e25438cc10002000112"},"asset_id":"514a21e00f7ca62513000110","bounds":{"width":"0.725","height":"0.01718213058419244","x":"0.056578947368421055","y":"0.570446735395189"},"data":{"character":"Bill Fagan","description":"","actor":"Henry Thompson"},"entity_id":"510feb5ac44ecc000200000c","created_at":"2013-03-31T20:47:47Z"}]},{"name":"Cast Member","entity_id":"510feb5ac44ecc000200000c","confidence":"medium","asset_id":"514a21e00f7ca62513000110","bounds":{"width":"0.717","height":"0.011254924029262802","x":"0.056","y":"0.5880697805289814"},"data":{"character":{"value":"\"Babe Merrill\"","confidence":"medium"},"description":{"value":"","confidence":"medium"},"actor":{"value":"George Abbott","confidence":"medium"}},"revisions":[{"id":"51511a8d74cbf600020014c8","user":{"name":"User.514a3a0a94f50b0002000f1f","id":"514a3a0a94f50b0002000f1f"},"asset_id":"514a21e00f7ca62513000110","bounds":{"width":"0.717","height":"0.011254924029262802","x":"0.056","y":"0.5880697805289814"},"data":{"character":"\"Babe Merrill\"","description":"","actor":"George Abbott"},"entity_id":"510feb5ac44ecc000200000c","created_at":"2013-03-26T03:48:29Z"},{"id":"5158a0f3bf701100020028ed","user":{"name":"User.51583e25438cc10002000112","id":"51583e25438cc10002000112"},"asset_id":"514a21e00f7ca62513000110","bounds":{"width":"0.7486842105263158","height":"0.01718213058419244","x":"0.056578947368421055","y":"0.5816151202749141"},"data":{"character":"\"Babe Merrill\"","description":"","actor":"George Abbott"},"entity_id":"510feb5ac44ecc000200000c","created_at":"2013-03-31T20:47:47Z"}]},{"name":"Cast Member","entity_id":"510feb5ac44ecc000200000c","confidence":"medium","asset_id":"514a21e00f7ca62513000110","bounds":{"width":"0.722","height":"0.011254924029262802","x":"0.056","y":"0.5402363534046145"},"data":{"character":{"value":"Keen Fitzpatrick","confidence":"medium"},"description":{"value":"","confidence":"medium"},"actor":{"value":"Walter Regan","confidence":"medium"}},"revisions":[{"id":"51511a8d74cbf600020014d0","user":{"name":"User.514a3a0a94f50b0002000f1f","id":"514a3a0a94f50b0002000f1f"},"asset_id":"514a21e00f7ca62513000110","bounds":{"width":"0.722","height":"0.011254924029262802","x":"0.056","y":"0.5402363534046145"},"data":{"character":"Keen Fitzpatrick","description":"","actor":"Walter Regan"},"entity_id":"510feb5ac44ecc000200000c","created_at":"2013-03-26T03:48:29Z"},{"id":"5158a0f3bf701100020028e5","user":{"name":"User.51583e25438cc10002000112","id":"51583e25438cc10002000112"},"asset_id":"514a21e00f7ca62513000110","bounds":{"width":"0.7210526315789474","height":"0.01718213058419244","x":"0.056578947368421055","y":"0.5343642611683849"},"data":{"character":"Keen Fitzpatrick","description":"","actor":"Walter Regan"},"entity_id":"510feb5ac44ecc000200000c","created_at":"2013-03-31T20:47:47Z"}]},{"name":"Cast Member","entity_id":"510feb5ac44ecc000200000c","confidence":"medium","asset_id":"514a21e00f7ca62513000110","bounds":{"width":"0.721","height":"0.011254924029262802","x":"0.056","y":"0.6004501969611705"},"data":{"character":{"value":"\"Chesty\" Sanborn","confidence":"medium"},"description":{"value":"","confidence":"medium"},"actor":{"value":"Frederick Wallace","confidence":"medium"}},"revisions":[{"id":"51511a8d74cbf600020014c6","user":{"name":"User.514a3a0a94f50b0002000f1f","id":"514a3a0a94f50b0002000f1f"},"asset_id":"514a21e00f7ca62513000110","bounds":{"width":"0.721","height":"0.011254924029262802","x":"0.056","y":"0.6004501969611705"},"data":{"character":"\"Chesty\" Sanborn","description":"","actor":"Frederick Wallace"},"entity_id":"510feb5ac44ecc000200000c","created_at":"2013-03-26T03:48:29Z"},{"id":"5158a0f3bf701100020028ef","user":{"name":"User.51583e25438cc10002000112","id":"51583e25438cc10002000112"},"asset_id":"514a21e00f7ca62513000110","bounds":{"width":"0.7223684210526315","height":"0.01718213058419244","x":"0.056578947368421055","y":"0.5945017182130584"},"data":{"character":"\"Chesty\" Sanborn","description":"","actor":"Frederick Wallace"},"entity_id":"510feb5ac44ecc000200000c","created_at":"2013-03-31T20:47:47Z"}]},{"name":"Cast Member","entity_id":"510feb5ac44ecc000200000c","confidence":"medium","asset_id":"514a21e00f7ca62513000110","bounds":{"width":"0.72","height":"0.011254924029262802","x":"0.055","y":"0.6246482836240855"},"data":{"character":{"value":"Mrs. John W. Cannell","confidence":"medium"},"description":{"value":"","confidence":"medium"},"actor":{"value":"Alice Wilson","confidence":"medium"}},"revisions":[{"id":"51511a8c74cbf600020014c2","user":{"name":"User.514a3a0a94f50b0002000f1f","id":"514a3a0a94f50b0002000f1f"},"asset_id":"514a21e00f7ca62513000110","bounds":{"width":"0.72","height":"0.011254924029262802","x":"0.055","y":"0.6246482836240855"},"data":{"character":"Mrs. John W. Cannell","description":"","actor":"Alice Wilson"},"entity_id":"510feb5ac44ecc000200000c","created_at":"2013-03-26T03:48:29Z"},{"id":"5158a0f3bf701100020028f3","user":{"name":"User.51583e25438cc10002000112","id":"51583e25438cc10002000112"},"asset_id":"514a21e00f7ca62513000110","bounds":{"width":"0.7276315789473684","height":"0.01718213058419244","x":"0.05526315789473684","y":"0.6176975945017182"},"data":{"character":"Mrs. John W. Cannell","description":"","actor":"Alice Wilson"},"entity_id":"510feb5ac44ecc000200000c","created_at":"2013-03-31T20:47:47Z"}]},{"name":"Cast Member","entity_id":"510feb5ac44ecc000200000c","confidence":"medium","asset_id":"514a21e00f7ca62513000110","bounds":{"width":"0.719","height":"0.011254924029262802","x":"0.055","y":"0.6370287000562747"},"data":{"character":{"value":"Jane Wentworth","confidence":"medium"},"description":{"value":"","confidence":"medium"},"actor":{"value":"Grace Barbour","confidence":"medium"}},"revisions":[{"id":"51511a8c74cbf600020014c0","user":{"name":"User.514a3a0a94f50b0002000f1f","id":"514a3a0a94f50b0002000f1f"},"asset_id":"514a21e00f7ca62513000110","bounds":{"width":"0.719","height":"0.011254924029262802","x":"0.055","y":"0.6370287000562747"},"data":{"character":"Jane Wentworth","description":"","actor":"Grace Barbour"},"entity_id":"510feb5ac44ecc000200000c","created_at":"2013-03-26T03:48:28Z"},{"id":"5158a0f3bf701100020028f5","user":{"name":"User.51583e25438cc10002000112","id":"51583e25438cc10002000112"},"asset_id":"514a21e00f7ca62513000110","bounds":{"width":"0.7355263157894737","height":"0.01718213058419244","x":"0.05526315789473684","y":"0.6297250859106529"},"data":{"character":"Jane Wentworth","description":"","actor":"Grace Barbour"},"entity_id":"510feb5ac44ecc000200000c","created_at":"2013-03-31T20:47:47Z"}]},{"name":"Cast Member","entity_id":"510feb5ac44ecc000200000c","confidence":"low","asset_id":"514a21e00f7ca62513000110","bounds":{"width":"0.718","height":"0.011254924029262802","x":"0.056","y":"0.6606640405177265"},"data":{"character":{"value":"Grace Buchanan","confidence":"low"},"description":{"value":"","confidence":"low"},"actor":{"value":"Alison Skinner","confidence":"low"}},"revisions":[{"id":"51511a8c74cbf600020014bc","user":{"name":"User.514a3a0a94f50b0002000f1f","id":"514a3a0a94f50b0002000f1f"},"asset_id":"514a21e00f7ca62513000110","bounds":{"width":"0.718","height":"0.011254924029262802","x":"0.056","y":"0.6606640405177265"},"data":{"character":"Grace Buchanan","description":"","actor":"Alison Skinner"},"entity_id":"510feb5ac44ecc000200000c","created_at":"2013-03-26T03:48:28Z"}]},{"name":"Cast Member","entity_id":"510feb5ac44ecc000200000c","confidence":"low","asset_id":"514a21e00f7ca62513000110","bounds":{"width":"0.719","height":"0.011254924029262802","x":"0.055","y":"0.6122678671918964"},"data":{"character":{"value":"Helen Steele","confidence":"low"},"description":{"value":"","confidence":"low"},"actor":{"value":"Doris Olsson","confidence":"low"}},"revisions":[{"id":"51511a8d74cbf600020014c4","user":{"name":"User.514a3a0a94f50b0002000f1f","id":"514a3a0a94f50b0002000f1f"},"asset_id":"514a21e00f7ca62513000110","bounds":{"width":"0.719","height":"0.011254924029262802","x":"0.055","y":"0.6122678671918964"},"data":{"character":"Helen Steele","description":"","actor":"Doris Olsson"},"entity_id":"510feb5ac44ecc000200000c","created_at":"2013-03-26T03:48:29Z"}]},{"name":"Cast Member","entity_id":"510feb5ac44ecc000200000c","confidence":"medium","asset_id":"514a21e00f7ca62513000110","bounds":{"width":"0.716","height":"0.011254924029262802","x":"0.055","y":"0.5053460889138999"},"data":{"character":{"value":"Henry Tracey","confidence":"medium"},"description":{"value":"","confidence":"medium"},"actor":{"value":"Henry Miller, Jr.","confidence":"medium"}},"revisions":[{"id":"51511a8c74cbf600020014b8","user":{"name":"User.514a3a0a94f50b0002000f1f","id":"514a3a0a94f50b0002000f1f"},"asset_id":"514a21e00f7ca62513000110","bounds":{"width":"0.716","height":"0.011254924029262802","x":"0.055","y":"0.5053460889138999"},"data":{"character":"Henry Tracey","description":"","actor":"Henry Miller, Jr."},"entity_id":"510feb5ac44ecc000200000c","created_at":"2013-03-26T03:48:28Z"},{"id":"5158a0f3bf701100020028df","user":{"name":"User.51583e25438cc10002000112","id":"51583e25438cc10002000112"},"asset_id":"514a21e00f7ca62513000110","bounds":{"width":"0.7171052631578947","height":"0.01718213058419244","x":"0.056578947368421055","y":"0.49828178694158076"},"data":{"character":"Henry Tracey","description":"","actor":"Henry Miller, Jr."},"entity_id":"510feb5ac44ecc000200000c","created_at":"2013-03-31T20:47:47Z"}]},{"name":"Cast Member","entity_id":"510feb5ac44ecc000200000c","confidence":"medium","asset_id":"514a21e00f7ca62513000110","bounds":{"width":"0.721","height":"0.011817670230725942","x":"0.055","y":"0.49296567248171075"},"data":{"character":{"value":"John W. Cannell","confidence":"medium"},"description":{"value":"","confidence":"medium"},"actor":{"value":"Thomas F. Tracey","confidence":"medium"}},"revisions":[{"id":"51511a8c74cbf600020014ba","user":{"name":"User.514a3a0a94f50b0002000f1f","id":"514a3a0a94f50b0002000f1f"},"asset_id":"514a21e00f7ca62513000110","bounds":{"width":"0.721","height":"0.011817670230725942","x":"0.055","y":"0.49296567248171075"},"data":{"character":"John W. Cannell","description":"","actor":"Thomas F. Tracey"},"entity_id":"510feb5ac44ecc000200000c","created_at":"2013-03-26T03:48:28Z"},{"id":"5158a0f3bf701100020028dd","user":{"name":"User.51583e25438cc10002000112","id":"51583e25438cc10002000112"},"asset_id":"514a21e00f7ca62513000110","bounds":{"width":"0.7421052631578947","height":"0.020618556701030927","x":"0.05526315789473684","y":"0.4845360824742268"},"data":{"character":"John W. Cannell","description":"","actor":"Thomas F. Tracey"},"entity_id":"510feb5ac44ecc000200000c","created_at":"2013-03-31T20:47:47Z"}]},{"name":"Cast Member","entity_id":"510feb5ac44ecc000200000c","confidence":"medium","asset_id":"514a21e00f7ca62513000110","bounds":{"width":"0.718","height":"0.011254924029262802","x":"0.055","y":"0.4800225098480585"},"data":{"character":{"value":"Jack Craigen","confidence":"medium"},"description":{"value":"","confidence":"medium"},"actor":{"value":"Lewis S. Stone","confidence":"medium"}},"revisions":[{"id":"51511a8c74cbf600020014b6","user":{"name":"User.514a3a0a94f50b0002000f1f","id":"514a3a0a94f50b0002000f1f"},"asset_id":"514a21e00f7ca62513000110","bounds":{"width":"0.718","height":"0.011254924029262802","x":"0.055","y":"0.4800225098480585"},"data":{"character":"Jack Craigen","description":"","actor":"Lewis S. Stone"},"entity_id":"510feb5ac44ecc000200000c","created_at":"2013-03-26T03:48:28Z"},{"id":"5158a0f3bf701100020028db","user":{"name":"User.51583e25438cc10002000112","id":"51583e25438cc10002000112"},"asset_id":"514a21e00f7ca62513000110","bounds":{"width":"0.7236842105263158","height":"0.01718213058419244","x":"0.05526315789473684","y":"0.4742268041237113"},"data":{"character":"Jack Craigen","description":"","actor":"Lewis S. Stone"},"entity_id":"510feb5ac44ecc000200000c","created_at":"2013-03-31T20:47:47Z"}]},{"name":"Cast Member","entity_id":"510feb5ac44ecc000200000c","confidence":"medium","asset_id":"514a21e00f7ca62513000110","bounds":{"width":"0.722","height":"0.011254924029262802","x":"0.056","y":"0.5284186831738886"},"data":{"character":{"value":"Stephen Weatherbee","confidence":"medium"},"description":{"value":"","confidence":"medium"},"actor":{"value":"Henry Stockbridge","confidence":"medium"}},"revisions":[{"id":"51511a8d74cbf600020014d2","user":{"name":"User.514a3a0a94f50b0002000f1f","id":"514a3a0a94f50b0002000f1f"},"asset_id":"514a21e00f7ca62513000110","bounds":{"width":"0.722","height":"0.011254924029262802","x":"0.056","y":"0.5284186831738886"},"data":{"character":"Stephen Weatherbee","description":"","actor":"Henry Stockbridge"},"entity_id":"510feb5ac44ecc000200000c","created_at":"2013-03-26T03:48:29Z"},{"id":"5158a0f3bf701100020028e3","user":{"name":"User.51583e25438cc10002000112","id":"51583e25438cc10002000112"},"asset_id":"514a21e00f7ca62513000110","bounds":{"width":"0.7342105263157894","height":"0.01718213058419244","x":"0.056578947368421055","y":"0.5223367697594502"},"data":{"character":"Stephen Weatherbee","description":"","actor":"Henry Stockbridge"},"entity_id":"510feb5ac44ecc000200000c","created_at":"2013-03-31T20:47:47Z"}]},{"name":"Cast Member","entity_id":"510feb5ac44ecc000200000c","confidence":"low","asset_id":"514a21e00f7ca62513000110","bounds":{"width":"0.1626984126984127","height":"0.009067357512953367","x":"0.6130952380952381","y":"0.6139896373056994"},"data":{"character":{"value":"Helen Steele","confidence":"low"},"description":{"value":"","confidence":"low"},"actor":{"value":"Doris Olsson","confidence":"low"}},"revisions":[{"id":"514c7bebd704c2000200c78c","user":{"name":"User.514c78887a2a4e000200d0fe","id":"514c78887a2a4e000200d0fe"},"asset_id":"514a21e00f7ca62513000110","bounds":{"width":"0.1626984126984127","height":"0.009067357512953367","x":"0.6130952380952381","y":"0.6139896373056994"},"data":{"character":"Helen Steele","description":"","actor":"Doris Olsson"},"entity_id":"510feb5ac44ecc000200000c","created_at":"2013-03-22T15:42:35Z"}]},{"name":"Cast Member","entity_id":"510feb5ac44ecc000200000c","confidence":"low","asset_id":"514a21e00f7ca62513000110","bounds":{"width":"0.1626984126984127","height":"0.010362694300518135","x":"0.6111111111111112","y":"0.5077720207253886"},"data":{"character":{"value":"Henry Tracey","confidence":"low"},"description":{"value":"","confidence":"low"},"actor":{"value":"Henry Miller, Jr.","confidence":"low"}},"revisions":[{"id":"514c7bebd704c2000200c774","user":{"name":"User.514c78887a2a4e000200d0fe","id":"514c78887a2a4e000200d0fe"},"asset_id":"514a21e00f7ca62513000110","bounds":{"width":"0.1626984126984127","height":"0.010362694300518135","x":"0.6111111111111112","y":"0.5077720207253886"},"data":{"character":"Henry Tracey","description":"","actor":"Henry Miller, Jr."},"entity_id":"510feb5ac44ecc000200000c","created_at":"2013-03-22T15:42:35Z"}]},{"name":"Cast Member","entity_id":"510feb5ac44ecc000200000c","confidence":"low","asset_id":"514a21e00f7ca62513000110","bounds":{"width":"0.19444444444444445","height":"0.009067357512953367","x":"0.5833333333333334","y":"0.483160621761658"},"data":{"character":{"value":"Jack Craigen","confidence":"low"},"description":{"value":"","confidence":"low"},"actor":{"value":"Lewis S. Stone","confidence":"low"}},"revisions":[{"id":"514c7bebd704c2000200c770","user":{"name":"User.514c78887a2a4e000200d0fe","id":"514c78887a2a4e000200d0fe"},"asset_id":"514a21e00f7ca62513000110","bounds":{"width":"0.19444444444444445","height":"0.009067357512953367","x":"0.5833333333333334","y":"0.483160621761658"},"data":{"character":"Jack Craigen","description":"","actor":"Lewis S. Stone"},"entity_id":"510feb5ac44ecc000200000c","created_at":"2013-03-22T15:42:35Z"}]},{"name":"Cast Member","entity_id":"510feb5ac44ecc000200000c","confidence":"low","asset_id":"514a21e00f7ca62513000110","bounds":{"width":"0.13690476190476192","height":"0.007772020725388601","x":"0.6369047619047619","y":"0.6269430051813472"},"data":{"character":{"value":"Mrs. John W. Cannell","confidence":"low"},"description":{"value":"","confidence":"low"},"actor":{"value":"Alice Wilson","confidence":"low"}},"revisions":[{"id":"514c7bebd704c2000200c78e","user":{"name":"User.514c78887a2a4e000200d0fe","id":"514c78887a2a4e000200d0fe"},"asset_id":"514a21e00f7ca62513000110","bounds":{"width":"0.13690476190476192","height":"0.007772020725388601","x":"0.6369047619047619","y":"0.6269430051813472"},"data":{"character":"Mrs. John W. Cannell","description":"","actor":"Alice Wilson"},"entity_id":"510feb5ac44ecc000200000c","created_at":"2013-03-22T15:42:35Z"}]},{"name":"Cast Member","entity_id":"510feb5ac44ecc000200000c","confidence":"low","asset_id":"514a21e00f7ca62513000110","bounds":{"width":"0.17857142857142858","height":"0.010362694300518135","x":"0.5952380952380952","y":"0.5790155440414507"},"data":{"character":{"value":"Bill Fagan","confidence":"low"},"description":{"value":"","confidence":"low"},"actor":{"value":"Henry Thompson","confidence":"low"}},"revisions":[{"id":"514c7bebd704c2000200c786","user":{"name":"User.514c78887a2a4e000200d0fe","id":"514c78887a2a4e000200d0fe"},"asset_id":"514a21e00f7ca62513000110","bounds":{"width":"0.17857142857142858","height":"0.010362694300518135","x":"0.5952380952380952","y":"0.5790155440414507"},"data":{"character":"Bill Fagan","description":"","actor":"Henry Thompson"},"entity_id":"510feb5ac44ecc000200000c","created_at":"2013-03-22T15:42:35Z"}]},{"name":"Cast Member","entity_id":"510feb5ac44ecc000200000c","confidence":"low","asset_id":"514a21e00f7ca62513000110","bounds":{"width":"0.15873015873015872","height":"0.009067357512953367","x":"0.6170634920634921","y":"0.6386010362694301"},"data":{"character":{"value":"Jane Wentworth","confidence":"low"},"description":{"value":"","confidence":"low"},"actor":{"value":"Grace Barbour","confidence":"low"}},"revisions":[{"id":"514c7bebd704c2000200c790","user":{"name":"User.514c78887a2a4e000200d0fe","id":"514c78887a2a4e000200d0fe"},"asset_id":"514a21e00f7ca62513000110","bounds":{"width":"0.15873015873015872","height":"0.009067357512953367","x":"0.6170634920634921","y":"0.6386010362694301"},"data":{"character":"Jane Wentworth","description":"","actor":"Grace Barbour"},"entity_id":"510feb5ac44ecc000200000c","created_at":"2013-03-22T15:42:35Z"}]},{"name":"Cast Member","entity_id":"510feb5ac44ecc000200000c","confidence":"low","asset_id":"514a21e00f7ca62513000110","bounds":{"width":"0.15674603174603174","height":"0.009067357512953367","x":"0.6190476190476191","y":"0.5660621761658031"},"data":{"character":{"value":"Tim McMahon","confidence":"low"},"description":{"value":"","confidence":"low"},"actor":{"value":"Albert Sackett","confidence":"low"}},"revisions":[{"id":"514c7bebd704c2000200c784","user":{"name":"User.514c78887a2a4e000200d0fe","id":"514c78887a2a4e000200d0fe"},"asset_id":"514a21e00f7ca62513000110","bounds":{"width":"0.15674603174603174","height":"0.009067357512953367","x":"0.6190476190476191","y":"0.5660621761658031"},"data":{"character":"Tim McMahon","description":"","actor":"Albert Sackett"},"entity_id":"510feb5ac44ecc000200000c","created_at":"2013-03-22T15:42:35Z"}]},{"name":"Cast Member","entity_id":"510feb5ac44ecc000200000c","confidence":"low","asset_id":"514a21e00f7ca62513000110","bounds":{"width":"0.1388888888888889","height":"0.010362694300518135","x":"0.6349206349206349","y":"0.6502590673575129"},"data":{"character":{"value":"Amy Foster","confidence":"low"},"description":{"value":"","confidence":"low"},"actor":{"value":"Daisy Adams","confidence":"low"}},"revisions":[{"id":"514c7bebd704c2000200c792","user":{"name":"User.514c78887a2a4e000200d0fe","id":"514c78887a2a4e000200d0fe"},"asset_id":"514a21e00f7ca62513000110","bounds":{"width":"0.1388888888888889","height":"0.010362694300518135","x":"0.6349206349206349","y":"0.6502590673575129"},"data":{"character":"Amy Foster","description":"","actor":"Daisy Adams"},"entity_id":"510feb5ac44ecc000200000c","created_at":"2013-03-22T15:42:35Z"}]},{"name":"Cast Member","entity_id":"510feb5ac44ecc000200000c","confidence":"low","asset_id":"514a21e00f7ca62513000110","bounds":{"width":"0.18055555555555555","height":"0.010362694300518135","x":"0.5952380952380952","y":"0.5906735751295337"},"data":{"character":{"value":"\"Babe Merrill\"","confidence":"low"},"description":{"value":"","confidence":"low"},"actor":{"value":"George Abbott","confidence":"low"}},"revisions":[{"id":"514c7bebd704c2000200c788","user":{"name":"User.514c78887a2a4e000200d0fe","id":"514c78887a2a4e000200d0fe"},"asset_id":"514a21e00f7ca62513000110","bounds":{"width":"0.18055555555555555","height":"0.010362694300518135","x":"0.5952380952380952","y":"0.5906735751295337"},"data":{"character":"\"Babe Merrill\"","description":"","actor":"George Abbott"},"entity_id":"510feb5ac44ecc000200000c","created_at":"2013-03-22T15:42:35Z"}]},{"name":"Cast Member","entity_id":"510feb5ac44ecc000200000c","confidence":"low","asset_id":"514a21e00f7ca62513000110","bounds":{"width":"0.1527777777777778","height":"0.010362694300518135","x":"0.623015873015873","y":"0.5544041450777202"},"data":{"character":{"value":"Boney","confidence":"low"},"description":{"value":"","confidence":"low"},"actor":{"value":"Frank Sylvester","confidence":"low"}},"revisions":[{"id":"514c7bebd704c2000200c782","user":{"name":"User.514c78887a2a4e000200d0fe","id":"514c78887a2a4e000200d0fe"},"asset_id":"514a21e00f7ca62513000110","bounds":{"width":"0.1527777777777778","height":"0.010362694300518135","x":"0.623015873015873","y":"0.5544041450777202"},"data":{"character":"Boney","description":"","actor":"Frank Sylvester"},"entity_id":"510feb5ac44ecc000200000c","created_at":"2013-03-22T15:42:35Z"}]},{"name":"Cast Member","entity_id":"510feb5ac44ecc000200000c","confidence":"low","asset_id":"514a21e00f7ca62513000110","bounds":{"width":"0.1746031746031746","height":"0.010362694300518135","x":"0.6011904761904762","y":"0.5427461139896373"},"data":{"character":{"value":"Keen Fitzpatrick","confidence":"low"},"description":{"value":"","confidence":"low"},"actor":{"value":"Walter Regan","confidence":"low"}},"revisions":[{"id":"514c7bebd704c2000200c780","user":{"name":"User.514c78887a2a4e000200d0fe","id":"514c78887a2a4e000200d0fe"},"asset_id":"514a21e00f7ca62513000110","bounds":{"width":"0.1746031746031746","height":"0.010362694300518135","x":"0.6011904761904762","y":"0.5427461139896373"},"data":{"character":"Keen Fitzpatrick","description":"","actor":"Walter Regan"},"entity_id":"510feb5ac44ecc000200000c","created_at":"2013-03-22T15:42:35Z"}]},{"name":"Cast Member","entity_id":"510feb5ac44ecc000200000c","confidence":"low","asset_id":"514a21e00f7ca62513000110","bounds":{"width":"0.17857142857142858","height":"0.009067357512953367","x":"0.5972222222222222","y":"0.5194300518134715"},"data":{"character":{"value":"Sidney Parker","confidence":"low"},"description":{"value":"","confidence":"low"},"actor":{"value":"Albert Sackett","confidence":"low"}},"revisions":[{"id":"514c7bebd704c2000200c77c","user":{"name":"User.514c78887a2a4e000200d0fe","id":"514c78887a2a4e000200d0fe"},"asset_id":"514a21e00f7ca62513000110","bounds":{"width":"0.17857142857142858","height":"0.009067357512953367","x":"0.5972222222222222","y":"0.5194300518134715"},"data":{"character":"Sidney Parker","description":"","actor":"Albert Sackett"},"entity_id":"510feb5ac44ecc000200000c","created_at":"2013-03-22T15:42:35Z"}]},{"name":"Cast Member","entity_id":"510feb5ac44ecc000200000c","confidence":"low","asset_id":"514a21e00f7ca62513000110","bounds":{"width":"0.1984126984126984","height":"0.010362694300518135","x":"0.5773809523809523","y":"0.5310880829015544"},"data":{"character":{"value":"Stephen Weatherbee","confidence":"low"},"description":{"value":"","confidence":"low"},"actor":{"value":"Henry Stockbridge","confidence":"low"}},"revisions":[{"id":"514c7bebd704c2000200c77e","user":{"name":"User.514c78887a2a4e000200d0fe","id":"514c78887a2a4e000200d0fe"},"asset_id":"514a21e00f7ca62513000110","bounds":{"width":"0.1984126984126984","height":"0.010362694300518135","x":"0.5773809523809523","y":"0.5310880829015544"},"data":{"character":"Stephen Weatherbee","description":"","actor":"Henry Stockbridge"},"entity_id":"510feb5ac44ecc000200000c","created_at":"2013-03-22T15:42:35Z"}]},{"name":"Cast Member","entity_id":"510feb5ac44ecc000200000c","confidence":"low","asset_id":"514a21e00f7ca62513000110","bounds":{"width":"0.17063492063492064","height":"0.010362694300518135","x":"0.6051587301587301","y":"0.4948186528497409"},"data":{"character":{"value":"John W. Cannell","confidence":"low"},"description":{"value":"","confidence":"low"},"actor":{"value":"Thomas F. Tracey","confidence":"low"}},"revisions":[{"id":"514c7bebd704c2000200c772","user":{"name":"User.514c78887a2a4e000200d0fe","id":"514c78887a2a4e000200d0fe"},"asset_id":"514a21e00f7ca62513000110","bounds":{"width":"0.17063492063492064","height":"0.010362694300518135","x":"0.6051587301587301","y":"0.4948186528497409"},"data":{"character":"John W. Cannell","description":"","actor":"Thomas F. Tracey"},"entity_id":"510feb5ac44ecc000200000c","created_at":"2013-03-22T15:42:35Z"}]},{"name":"Cast Member","entity_id":"510feb5ac44ecc000200000c","confidence":"low","asset_id":"514a21e00f7ca62513000110","bounds":{"width":"0.17261904761904762","height":"0.009067357512953367","x":"0.6031746031746031","y":"0.6023316062176166"},"data":{"character":{"value":"\"Chesty\" Sanborn","confidence":"low"},"description":{"value":"","confidence":"low"},"actor":{"value":"Frederick Wallace","confidence":"low"}},"revisions":[{"id":"514c7bebd704c2000200c78a","user":{"name":"User.514c78887a2a4e000200d0fe","id":"514c78887a2a4e000200d0fe"},"asset_id":"514a21e00f7ca62513000110","bounds":{"width":"0.17261904761904762","height":"0.009067357512953367","x":"0.6031746031746031","y":"0.6023316062176166"},"data":{"character":"\"Chesty\" Sanborn","description":"","actor":"Frederick Wallace"},"entity_id":"510feb5ac44ecc000200000c","created_at":"2013-03-22T15:42:35Z"}]},{"name":"Cast Member","entity_id":"510feb5ac44ecc000200000c","confidence":"low","asset_id":"514a21e00f7ca62513000110","bounds":{"width":"0.16071428571428573","height":"0.010362694300518135","x":"0.6150793650793651","y":"0.6619170984455959"},"data":{"character":{"value":"Grace Buchanan","confidence":"low"},"description":{"value":"","confidence":"low"},"actor":{"value":"Alison Skinner","confidence":"low"}},"revisions":[{"id":"514c7bebd704c2000200c794","user":{"name":"User.514c78887a2a4e000200d0fe","id":"514c78887a2a4e000200d0fe"},"asset_id":"514a21e00f7ca62513000110","bounds":{"width":"0.16071428571428573","height":"0.010362694300518135","x":"0.6150793650793651","y":"0.6619170984455959"},"data":{"character":"Grace Buchanan","description":"","actor":"Alison Skinner"},"entity_id":"510feb5ac44ecc000200000c","created_at":"2013-03-22T15:42:35Z"}]},{"name":"Cast Member","entity_id":"510feb5ac44ecc000200000c","confidence":"low","asset_id":"514a21e00f7ca62513000110","bounds":{"width":"0.7486842105263158","height":"0.022336769759450172","x":"0.056578947368421055","y":"0.6494845360824742"},"data":{"character":{"value":"Grace Buchanan","confidence":"low"},"description":{"value":"","confidence":"low"},"actor":{"value":"Alison Skinner","confidence":"low"}},"revisions":[{"id":"5158a0f3bf701100020028f9","user":{"name":"User.51583e25438cc10002000112","id":"51583e25438cc10002000112"},"asset_id":"514a21e00f7ca62513000110","bounds":{"width":"0.7486842105263158","height":"0.022336769759450172","x":"0.056578947368421055","y":"0.6494845360824742"},"data":{"character":"Grace Buchanan","description":"","actor":"Alison Skinner"},"entity_id":"510feb5ac44ecc000200000c","created_at":"2013-03-31T20:47:47Z"}]},{"name":"Cast Member","entity_id":"510feb5ac44ecc000200000c","confidence":"low","asset_id":"514a21e00f7ca62513000110","bounds":{"width":"0.7223684210526315","height":"0.024054982817869417","x":"0.05526315789473684","y":"0.5996563573883161"},"data":{"character":{"value":"Helen Steele","confidence":"low"},"description":{"value":"","confidence":"low"},"actor":{"value":"Doris Olsson","confidence":"low"}},"revisions":[{"id":"5158a0f3bf701100020028f1","user":{"name":"User.51583e25438cc10002000112","id":"51583e25438cc10002000112"},"asset_id":"514a21e00f7ca62513000110","bounds":{"width":"0.7223684210526315","height":"0.024054982817869417","x":"0.05526315789473684","y":"0.5996563573883161"},"data":{"character":"Helen Steele","description":"","actor":"Doris Olsson"},"entity_id":"510feb5ac44ecc000200000c","created_at":"2013-03-31T20:47:47Z"}]},{"name":"Production Staff","entity_id":"510feb5ac44ecc0002000010","confidence":"medium","asset_id":"514a21e10f7ca62513000112","bounds":{"width":"0.4503968253968254","height":"0.008962868117797696","x":"0.19246031746031747","y":"0.5211267605633803"},"data":{"role":{"value":"Director","confidence":"medium"},"name":{"value":"Holbrook Blinn","confidence":"medium"}},"revisions":[{"id":"514c7bebd704c2000200c798","user":{"name":"User.514c78887a2a4e000200d0fe","id":"514c78887a2a4e000200d0fe"},"asset_id":"514a21e10f7ca62513000112","bounds":{"width":"0.4503968253968254","height":"0.008962868117797696","x":"0.19246031746031747","y":"0.5211267605633803"},"data":{"role":"Director","name":"Holbrook Blinn"},"entity_id":"510feb5ac44ecc0002000010","created_at":"2013-03-22T15:42:35Z"},{"id":"5158a0f3bf7011000200290b","user":{"name":"User.51583e25438cc10002000112","id":"51583e25438cc10002000112"},"asset_id":"514a21e10f7ca62513000112","bounds":{"width":"0.45","height":"0.008488964346349745","x":"0.19210526315789472","y":"0.5212224108658744"},"data":{"role":"Director","name":"Holbrook Blinn"},"entity_id":"510feb5ac44ecc0002000010","created_at":"2013-03-31T20:47:47Z"}]},{"name":"Production Staff","entity_id":"510feb5ac44ecc0002000010","confidence":"medium","asset_id":"514a21e00f7ca62513000110","bounds":{"width":"0.32142857142857145","height":"0.010362694300518135","x":"0.25595238095238093","y":"0.31865284974093266"},"data":{"role":{"value":"Producer","confidence":"medium"},"name":{"value":"William Harris, Jr.","confidence":"medium"}},"revisions":[{"id":"514c7bebd704c2000200c776","user":{"name":"User.514c78887a2a4e000200d0fe","id":"514c78887a2a4e000200d0fe"},"asset_id":"514a21e00f7ca62513000110","bounds":{"width":"0.32142857142857145","height":"0.010362694300518135","x":"0.25595238095238093","y":"0.31865284974093266"},"data":{"role":"Producer","name":"William Harris, Jr."},"entity_id":"510feb5ac44ecc0002000010","created_at":"2013-03-22T15:42:35Z"},{"id":"5158a0f3bf701100020028d3","user":{"name":"User.51583e25438cc10002000112","id":"51583e25438cc10002000112"},"asset_id":"514a21e00f7ca62513000110","bounds":{"width":"0.3223684210526316","height":"0.010309278350515463","x":"0.25526315789473686","y":"0.31958762886597935"},"data":{"role":"Producer","name":"William Harris, Jr."},"entity_id":"510feb5ac44ecc0002000010","created_at":"2013-03-31T20:47:47Z"}]},{"name":"Production Staff","entity_id":"510feb5ac44ecc0002000010","confidence":"low","asset_id":"514a21e10f7ca62513000112","bounds":{"width":"0.5099206349206349","height":"0.05121638924455826","x":"0.21031746031746032","y":"0.5736235595390525"},"data":{"role":{"value":"Musical Director","confidence":"low"},"name":{"value":"M. P. Krueger","confidence":"low"}},"revisions":[{"id":"514c7bebd704c2000200c79a","user":{"name":"User.514c78887a2a4e000200d0fe","id":"514c78887a2a4e000200d0fe"},"asset_id":"514a21e10f7ca62513000112","bounds":{"width":"0.5099206349206349","height":"0.05121638924455826","x":"0.21031746031746032","y":"0.5736235595390525"},"data":{"role":"Musical Director","name":"M. P. Krueger"},"entity_id":"510feb5ac44ecc0002000010","created_at":"2013-03-22T15:42:35Z"}]},{"name":"Production Staff","entity_id":"510feb5ac44ecc0002000010","confidence":"low","asset_id":"514a21e00f7ca62513000110","bounds":{"width":"0.4027777777777778","height":"0.012953367875647668","x":"0.21428571428571427","y":"0.4015544041450777"},"data":{"role":{"value":"Playwrights","confidence":"low"},"name":{"value":"Chas. Goddard and Paul Dickey","confidence":"medium"}},"revisions":[{"id":"514c7bebd704c2000200c778","user":{"name":"User.514c78887a2a4e000200d0fe","id":"514c78887a2a4e000200d0fe"},"asset_id":"514a21e00f7ca62513000110","bounds":{"width":"0.4027777777777778","height":"0.012953367875647668","x":"0.21428571428571427","y":"0.4015544041450777"},"data":{"role":"Playwrights","name":"Chas. Goddard and Paul Dickey"},"entity_id":"510feb5ac44ecc0002000010","created_at":"2013-03-22T15:42:35Z"},{"id":"5158a0f3bf701100020028d7","user":{"name":"User.51583e25438cc10002000112","id":"51583e25438cc10002000112"},"asset_id":"514a21e00f7ca62513000110","bounds":{"width":"0.4039473684210526","height":"0.012027491408934708","x":"0.21447368421052632","y":"0.4020618556701031"},"data":{"role":"Authors","name":"Chas. Goddard and Paul Dickey"},"entity_id":"510feb5ac44ecc0002000010","created_at":"2013-03-31T20:47:47Z"}]},{"name":"Production Staff","entity_id":"510feb5ac44ecc0002000010","confidence":"low","asset_id":"514a21e10f7ca62513000112","bounds":{"width":"0.32142857142857145","height":"0.0076824583866837385","x":"0.25793650793650796","y":"0.48911651728553135"},"data":{"role":{"value":"Scenery painter","confidence":"low"},"name":{"value":"H. Robert Law","confidence":"medium"}},"revisions":[{"id":"514c7bebd704c2000200c796","user":{"name":"User.514c78887a2a4e000200d0fe","id":"514c78887a2a4e000200d0fe"},"asset_id":"514a21e10f7ca62513000112","bounds":{"width":"0.32142857142857145","height":"0.0076824583866837385","x":"0.25793650793650796","y":"0.48911651728553135"},"data":{"role":"Scenery painter","name":"H. Robert Law"},"entity_id":"510feb5ac44ecc0002000010","created_at":"2013-03-22T15:42:35Z"},{"id":"5158a0f3bf70110002002907","user":{"name":"User.51583e25438cc10002000112","id":"51583e25438cc10002000112"},"asset_id":"514a21e10f7ca62513000112","bounds":{"width":"0.3223684210526316","height":"0.008488964346349745","x":"0.2565789473684211","y":"0.48896434634974534"},"data":{"role":"Scenery Painter","name":"H. Robert Law"},"entity_id":"510feb5ac44ecc0002000010","created_at":"2013-03-31T20:47:47Z"}]},{"name":"Production Staff","entity_id":"510feb5ac44ecc0002000010","confidence":"low","asset_id":"514a21e10f7ca62513000112","bounds":{"width":"0.5105263157894737","height":"0.019524617996604414","x":"0.21052631578947367","y":"0.6052631578947368"},"data":{"role":{"value":"Musical Director","confidence":"low"},"name":{"value":"M. P. Krueger","confidence":"low"}},"revisions":[{"id":"5158a0f3bf7011000200290d","user":{"name":"User.51583e25438cc10002000112","id":"51583e25438cc10002000112"},"asset_id":"514a21e10f7ca62513000112","bounds":{"width":"0.5105263157894737","height":"0.019524617996604414","x":"0.21052631578947367","y":"0.6052631578947368"},"data":{"role":"Musical Director","name":"M. P. Krueger"},"entity_id":"510feb5ac44ecc0002000010","created_at":"2013-03-31T20:47:47Z"}]},{"name":"Production Staff","entity_id":"510feb5ac44ecc0002000010","confidence":"low","asset_id":"514a21e00f7ca62513000110","bounds":{"width":"0.6552631578947369","height":"0.011168384879725086","x":"0.08947368421052631","y":"0.13058419243986255"},"data":{"role":{"value":"Lessee and Manager","confidence":"low"},"name":{"value":"Leo C. Teller","confidence":"low"}},"revisions":[{"id":"5158a0f2bf701100020028cf","user":{"name":"User.51583e25438cc10002000112","id":"51583e25438cc10002000112"},"asset_id":"514a21e00f7ca62513000110","bounds":{"width":"0.6552631578947369","height":"0.011168384879725086","x":"0.08947368421052631","y":"0.13058419243986255"},"data":{"role":"Lessee and Manager","name":"Leo C. Teller"},"entity_id":"510feb5ac44ecc0002000010","created_at":"2013-03-31T20:47:46Z"}]},{"name":"Location","entity_id":"510feb5ac44ecc000200000a","confidence":"medium","asset_id":"514a21e00f7ca62513000110","bounds":{"width":"0.2837301587301587","height":"0.011658031088082901","x":"0.2757936507936508","y":"0.11917098445595854"},"data":{"location":{"value":"Broadway and Myrtle Avenue","confidence":"medium"}},"revisions":[{"id":"514c7bebd704c2000200c76e","user":{"name":"User.514c78887a2a4e000200d0fe","id":"514c78887a2a4e000200d0fe"},"asset_id":"514a21e00f7ca62513000110","bounds":{"width":"0.2837301587301587","height":"0.011658031088082901","x":"0.2757936507936508","y":"0.11917098445595854"},"data":{"location":"Broadway and Myrtle Avenue"},"entity_id":"510feb5ac44ecc000200000a","created_at":"2013-03-22T15:42:35Z"},{"id":"5158a0f2bf701100020028cd","user":{"name":"User.51583e25438cc10002000112","id":"51583e25438cc10002000112"},"asset_id":"514a21e00f7ca62513000110","bounds":{"width":"0.28289473684210525","height":"0.012027491408934708","x":"0.27631578947368423","y":"0.11855670103092783"},"data":{"location":"Broadway and Myrtle Avenue"},"entity_id":"510feb5ac44ecc000200000a","created_at":"2013-03-31T20:47:46Z"}]},{"name":"Theater Name","entity_id":"510feb5ac44ecc0002000008","confidence":"low","asset_id":"514a21e00f7ca62513000110","bounds":{"width":"0.2976190476190476","height":"0.018134715025906734","x":"0.2718253968253968","y":"0.05310880829015544"},"data":{"theater":{"value":"Teller's Broadway Theatre","confidence":"low"}},"revisions":[{"id":"514c7bebd704c2000200c76c","user":{"name":"User.514c78887a2a4e000200d0fe","id":"514c78887a2a4e000200d0fe"},"asset_id":"514a21e00f7ca62513000110","bounds":{"width":"0.2976190476190476","height":"0.018134715025906734","x":"0.2718253968253968","y":"0.05310880829015544"},"data":{"theater":"Teller's Broadway Theatre"},"entity_id":"510feb5ac44ecc0002000008","created_at":"2013-03-22T15:42:35Z"}]},{"name":"Theater Name","entity_id":"510feb5ac44ecc0002000008","confidence":"low","asset_id":"514a21e00f7ca62513000110","bounds":{"width":"0.7210526315789474","height":"0.06099656357388316","x":"0.06842105263157895","y":"0.05326460481099656"},"data":{"theater":{"value":"Teller's Broadway Theatre","confidence":"low"}},"revisions":[{"id":"5158a0f2bf701100020028cb","user":{"name":"User.51583e25438cc10002000112","id":"51583e25438cc10002000112"},"asset_id":"514a21e00f7ca62513000110","bounds":{"width":"0.7210526315789474","height":"0.06099656357388316","x":"0.06842105263157895","y":"0.05326460481099656"},"data":{"theater":"Teller's Broadway Theatre"},"entity_id":"510feb5ac44ecc0002000008","created_at":"2013-03-31T20:47:46Z"}]},{"name":"Show Date","entity_id":"510feb5ac44ecc0002000005","confidence":"low","asset_id":"514a21e00f7ca62513000110","bounds":{"width":"0.626984126984127","height":"0.011658031088082901","x":"0.10317460317460317","y":"0.24740932642487046"},"data":{"date_opened":{"value":"09/19/1914","confidence":"low"},"date_closed":{"value":"","confidence":"medium"}},"revisions":[{"id":"514c7bebd704c2000200c76a","user":{"name":"User.514c78887a2a4e000200d0fe","id":"514c78887a2a4e000200d0fe"},"asset_id":"514a21e00f7ca62513000110","bounds":{"width":"0.626984126984127","height":"0.011658031088082901","x":"0.10317460317460317","y":"0.24740932642487046"},"data":{"date_opened":"09/19/1914","date_closed":""},"entity_id":"510feb5ac44ecc0002000005","created_at":"2013-03-22T15:42:35Z"},{"id":"5158a0f3bf701100020028d1","user":{"name":"User.51583e25438cc10002000112","id":"51583e25438cc10002000112"},"asset_id":"514a21e00f7ca62513000110","bounds":{"width":"0.6289473684210526","height":"0.012027491408934708","x":"0.10263157894736842","y":"0.24742268041237114"},"data":{"date_opened":"September 19, 1914","date_closed":""},"entity_id":"510feb5ac44ecc0002000005","created_at":"2013-03-31T20:47:47Z"}]},{"name":"Show Title","entity_id":"510feb5ac44ecc0002000002","confidence":"medium","asset_id":"514a21e00f7ca62513000110","bounds":{"width":"0.7222222222222222","height":"0.042746113989637305","x":"0.05555555555555555","y":"0.3393782383419689"},"data":{"title":{"value":"The Misleading Lady","confidence":"medium"},"type":{"value":"main title","confidence":"medium"}},"revisions":[{"id":"514c7bebd704c2000200c768","user":{"name":"User.514c78887a2a4e000200d0fe","id":"514c78887a2a4e000200d0fe"},"asset_id":"514a21e00f7ca62513000110","bounds":{"width":"0.7222222222222222","height":"0.042746113989637305","x":"0.05555555555555555","y":"0.3393782383419689"},"data":{"title":"The Misleading Lady","type":"main title"},"entity_id":"510feb5ac44ecc0002000002","created_at":"2013-03-22T15:42:35Z"},{"id":"5158a0f3bf701100020028d5","user":{"name":"User.51583e25438cc10002000112","id":"51583e25438cc10002000112"},"asset_id":"514a21e00f7ca62513000110","bounds":{"width":"0.7210526315789474","height":"0.04209621993127148","x":"0.056578947368421055","y":"0.3393470790378007"},"data":{"title":"The Misleading Lady","type":"main title"},"entity_id":"510feb5ac44ecc0002000002","created_at":"2013-03-31T20:47:47Z"}]}]}}